Workbook

Sheet ToC
B11: Table of Contents
B13: # | C13: Sheet Name | D13: Link to Sheet
B14: 1 | C14: Valuation based on residual income approch | D14: residual income approch
B15: 2 | C15: Valuation based on cash flow | D15: valuation freecash flow
B16: 3 | C16: Valuation based on price ratio | D16: marketbased valuations
B17: 4 | C17: Forcasted Balancesheet | D17: balancesheet
B18: 5 | C18: Forcasted Income statement | D18: profitloss
B19: 6 | C19: Forcasted cash flow Statement | D19: cashflow
B20: 7 | C20: Forcasted Other Equity | D20: other equity
B21: 8 | C21: Forcasted Debt & Investment | D21: debt
B22: 9 | C22: Forcasted Working Capital | D22: WORKING CAPITAL
B23: 10 | C23: Forcasted Fixed assets | D23: PPE
B24: 11 | C24: Forcasted Revenue | D24: revenue
B25: 12 | C25: Forcasted Expenses | D25: expenses
B26: 13 | C26: Segment Analysis | D26: segmentrevenue

Sheet residual income approch
E7: =A35 -> reliance prices | G7: =C35 -> 2360.5663
A12: particulars | B12: 2021-22 | C12: 2022-23 | D12: 2023-24 | E12: 2024-25 | F12: 2025-26 | G12: 2026-27
A13: =balancesheet!A32 -> Equity Share Capital | B13: =balancesheet!F32 -> 6765 | C13: =balancesheet!G32 -> 6765 | D13: =balancesheet!H32 -> 6765 | E13: =balancesheet!I32 -> 6765 | F13: =balancesheet!J32 -> 6765 | G13: =balancesheet!K32 -> 6765
A14: =balancesheet!A33 -> Other Equity | B14: =balancesheet!F33 -> 772720 | C14: =balancesheet!G33 -> 864012.95 | D14: =balancesheet!H33 -> 968668.19 | E14: =balancesheet!I33 -> 1084911.4 | F14: =balancesheet!J33 -> 1214341.2 | G14: =balancesheet!K33 -> 1360794.9
A15: =balancesheet!A34 -> Non-Controlling Interest | B15: =balancesheet!F34 -> 109499 | C15: =balancesheet!G34 -> 119642.66 | D15: =balancesheet!H34 -> 131271.02 | E15: =balancesheet!I34 -> 144186.94 | F15: =balancesheet!J34 -> 158568.02 | G15: =balancesheet!K34 -> 174840.65
B16: =SUM(B13:B14) -> 779485 | C16: =SUM(C13:C14) -> 870777.95 | D16: =SUM(D13:D14) -> 975433.19 | E16: =SUM(E13:E14) -> 1091676.4 | F16: =SUM(F13:F14) -> 1221106.2 | G16: =SUM(G13:G14) -> 1367559.9
A17: no of shares | B17: 676.5 | C17: 676.5 | D17: 676.5 | E17: 676.5 | F17: 676.5 | G17: 676.5
A18: BVPS | B18: =B16/B17 -> 1152.2321 | C18: =C16/C17 -> 1287.181 | D18: =D16/D17 -> 1441.882 | E18: =E16/E17 -> 1613.7124 | F18: =F16/F17 -> 1805.0351 | G18: =G16/G17 -> 2021.5224
C20: =C18-B18+(C28/C17) -> 296.17824 | D20: =D18-C18+(D28/D17) -> 339.52901 | E20: =E18-D18+(E28/E17) -> 377.1235 | F20: =F18-E18+(F28/F17) -> 419.90411 | G20: =G18-F18+(G28/G17) -> 475.13403
C21: =B18*14% -> 161.31249 | D21: =C18*14% -> 180.20534 | E21: =D18*14% -> 201.86348 | F21: =E18*14% -> 225.91973 | G21: =F18*14% -> 252.70491
C22: =C28/C17 -> 161.22931 | D22: =D28/D17 -> 184.82799 | E22: =E28/E17 -> 205.29314 | F22: =F28/F17 -> 228.58144 | G22: =G28/G17 -> 258.64672
C23: =C22-C21 -> -0.083183471 | D23: =D22-D21 -> 4.6226451 | E23: =E22-E21 -> 3.4296584 | F23: =F22-F21 -> 2.6617078 | G23: =G22-G21 -> 5.9418143
C24: 1 | D24: 2 | E24: 3 | F24: 4 | G24: 5
C25: =-PV('valuation freecash flow'!$B$49,C24,0,C23,0) -> -0.073182529 | D25: =-PV('valuation freecash flow'!$B$49,D24,0,D23,0) -> 3.5779256 | E25: =-PV('valuation freecash flow'!$B$49,E24,0,E23,0) -> 2.3354039 | F25: =-PV('valuation freecash flow'!$B$49,F24,0,F23,0) -> 1.5945638 | G25: =-PV('valuation freecash flow'!$B$49,G24,0,G23,0) -> 3.1316338
B26: =SUM(B25:G25) -> 10.566344
A28: =profitloss!A35 -> Total Comprehensive Income for the Year | B28: =profitloss!F35 -> 90105 | C28: =profitloss!G35 -> 109071.63 | D28: =profitloss!H35 -> 125036.13 | E28: =profitloss!I35 -> 138880.81 | F28: =profitloss!J35 -> 154635.35 | G28: =profitloss!K35 -> 174974.51
A30: since reliance industries valuation is based on cost basis theredore average price of previous year is taken as market value
A31: reliance price | B31: 44651 | C31: 2650 | H31: =+H29 -> 0
B32: 44286 | C32: 2050
C33: =AVERAGE(C31:C32) -> 2350
A34: residual income approch | C34: =B26 -> 10.566344
A35: reliance prices | C35: =+C33+C34 -> 2360.5663

Sheet Sheet1
A3: particulard | B3: Column1 | C3: details
A4: Price | B4: #VALUE! | C4: {=_FV(B4,"Price")} -> 2537.25
A5: Beta | B5: #VALUE! | C5: {=_FV(B5,"Beta")} -> 1.0731
A6: Industry | B6: #VALUE! | C6: {=_FV(B6,"Industry")} -> Oil & Gas
A7: High | B7: #VALUE! | C7: {=_FV(B7,"52 week high",TRUE)} -> 2855
A8: Low | B8: #VALUE! | C8: {=_FV(B8,"52 week low",TRUE)} -> 2181
A9: marketcap | B9: #VALUE! | C9: {=_FV(B9,"Market cap",TRUE)} -> 16669470000000
A10: no of shares | B10: #VALUE! | C10: {=_FV(B10,"Shares outstanding",TRUE)} -> 6570968000
A11: P/E | B11: #VALUE! | C11: {=_FV(B11,"P/E",TRUE)} -> 25.45
A12: change | B12: #VALUE! | C12: {=_FV(B12,"Change")} -> 23.75

Sheet valuation freecash flow
A8: computatopn of weighted average cost of capital
A10: cost of equity
A11: CAPM Method
A12: Risk free rate | B12: 0.0735 | C12: (Source : world economiocs
A13: BETA | B13: 1.05 | C13: (Source : moneycontrol as well as calculated
A15: nifty returns past 5 years | B15: 28..65 | C15: 3.15 | D15: 12.02 | E15: 14.17 | F15: 24.12
A16: average | B16: =AVERAGE(B15:F15) -> 13.365
A18: return on market | B18: 0.13365
A20: CAPM Return | B20: =+B12+B13*(B18-B12) -> 0.1366575
A23: cost of debt | B23: =8.51%*(1-0.25) -> 0.063825
A25: elements of capital | B25: Column1 | C25: cpital employed | D25: % of debt | E25: cost of equity | F25: wacc
A26: equity | C26: =SUM(balancesheet!F32:F34) -> 888984 | D26: =C26/C28 -> 0.78014859 | E26: =B20 -> 0.1366575 | F26: =E26*D26 -> 0.10661316
A27: debt | C27: =debt!E7 -> 250522 | D27: =C27/C28 -> 0.21985141 | E27: =B23 -> 0.063825 | F27: =E27*D27 -> 0.014032016
C28: =SUM(C26:C27) -> 1139506 | D28: 1 | F28: =SUM(F26:F27) -> 0.12064517
A30: computation of free cash flows for firm
A31: particulars | B31: 2022-23E | C31: 2023-24E | D31: 2024-25E | E31: 2025-26E | F31: 2026-27E
A32: Profit after tax | B32: =profitloss!G28 -> 56074.126 | C32: =profitloss!H28 -> 73670.633 | D32: =profitloss!I28 -> 86699.311 | E32: =profitloss!J28 -> 102861.85 | F32: =profitloss!K28 -> 122997.01
A33: Ass Depriciation | B33: =profitloss!G17 -> 35113.252 | C33: =profitloss!H17 -> 36394.962 | D33: =profitloss!I17 -> 38187.399 | E33: =profitloss!J17 -> 40502.862 | F33: =profitloss!K17 -> 43377.203
A34: add interest after tax | B34: =+profitloss!G16*(1-0.25) -> 15774.65 | C34: =+profitloss!H16*(1-0.25) -> 17475.191 | D34: =+profitloss!I16*(1-0.25) -> 19573.484 | E34: =+profitloss!J16*(1-0.25) -> 22065.67 | F34: =+profitloss!K16*(1-0.25) -> 25011.543
B35: =SUM(B32:B34) -> 106962.03 | C35: =SUM(C32:C34) -> 127540.79 | D35: =SUM(D32:D34) -> 144460.19 | E35: =SUM(E32:E34) -> 165430.38 | F35: =SUM(F32:F34) -> 191385.75
A36: investment in PPE | B36: =+debt!B26 -> 38317.483 | C36: =+debt!C26 -> 58953.053 | D36: =+debt!D26 -> 69734.302 | E36: =+debt!E26 -> 81255.015 | F36: =+debt!F26 -> 93965.595
A37: investment in working capital | B37: =(balancesheet!G27-balancesheet!G54)-(balancesheet!F27-balancesheet!F54) -> 23881.727 | C37: =(balancesheet!H27-balancesheet!H54)-(balancesheet!G27-balancesheet!G54) -> 26399.872 | D37: =(balancesheet!I27-balancesheet!I54)-(balancesheet!H27-balancesheet!H54) -> 26067.562 | E37: =(balancesheet!J27-balancesheet!J54)-(balancesheet!I27-balancesheet!I54) -> 27898.212 | F37: =(balancesheet!K27-balancesheet!K54)-(balancesheet!J27-balancesheet!J54) -> 31793.949
A38: free cash flow of firm | B38: =+B35-B36-B37 -> 44762.818 | C38: =+C35-C36-C37 -> 42187.859 | D38: =+D35-D36-D37 -> 48658.331 | E38: =+E35-E36-E37 -> 56277.152 | F38: =+F35-F36-F37 -> 65626.209
A40: =A38 -> free cash flow of firm | B40: =B38 -> 44762.818 | C40: =C38 -> 42187.859 | D40: =D38 -> 48658.331 | E40: =E38 -> 56277.152 | F40: =F38 -> 65626.209
A41: =A34 -> add interest after tax | B41: =B34 -> 15774.65 | C41: =C34 -> 17475.191 | D41: =D34 -> 19573.484 | E41: =E34 -> 22065.67 | F41: =F34 -> 25011.543
A42: add net borrowings | B42: =debt!B31 -> 24777.671 | C42: =debt!C31 -> 31907.023 | D42: =debt!D31 -> 38036.087 | E42: =debt!E31 -> 45036.768 | F42: =debt!F31 -> 53159.016
A43: free cash flow of euity | B43: =+B40-B41+B42 -> 53765.838 | C43: =+C40-C41+C42 -> 56619.692 | D43: =+D40-D41+D42 -> 67120.934 | E43: =+E40-E41+E42 -> 79248.25 | F43: =+F40-F41+F42 -> 93773.682
A45: growth rate | B45: =B46*B47 -> 0.096523672
A46: retained earning | B46: =(profitloss!F35-profitloss!F53)/profitloss!F35 -> 0.95231119
A47: rate of return | B47: =profitloss!F35/'valuation freecash flow'!C26 -> 0.10135728
A49: cost of equity | B49: =B20 -> 0.1366575
A51: value at 5 year | F51: =+F43/(B49-B47) -> 2656461.7
A52: year | B52: 1 | C52: 2 | D52: 3 | E52: 4 | F52: 5
A53: cash flows | B53: =B43 -> 53765.838 | C53: =C43 -> 56619.692 | D53: =D43 -> 67120.934 | E53: =E43 -> 79248.25 | F53: =F51+F43 -> 2750235.4
B54: =-PV($B$49,B52,0,B53,0) -> 47301.706 | C54: =-PV($B$49,C52,0,C53,0) -> 43823.621 | D54: =-PV($B$49,D52,0,D53,0) -> 45705.57 | E54: =-PV($B$49,E52,0,E53,0) -> 47475.68 | F54: =-PV($B$49,F52,0,F53,0) -> 1449511.8
A55: value of reliance industries | B55: =SUM(B54:F54) -> 1633818.4
A56: no of shares | B56: 677
A57: value per share | B57: =+B55/B56 -> 2413.3211

Sheet marketbased valuations
A8: particulars | B8: 0 | C8: . | D8: .2 | F8: 2 | G8: 3 | H8: 1year | I8: 2year
A9: VALUATION based on Reliance Industries Ltd based on multiples | G9: =AVERAGE(M44,M53,M58) -> #VALUE!
A10: VALUATION based on Reliance Industries Ltd based on enterprise calue | F10: buy | H10: =H78 -> 2628.0002 | I10: =I78 -> 2272.7132
F11: target | H11: =H77 -> 2995.9203 | I11: =I77 -> 2953.6181
A12: STRENGTHS | H12: WEAKNESS
A14: Efficient in managing Assets to generate Profits - ROA improving since last 2 year | I14: Decline in Net Profit with falling Profit Margin (QoQ)
A15: Company with Low Debt | I15: Decline in Quarterly Net Profit with falling Profit Margin (YoY)
A16: Increasing Revenue every Quarter for the past 4 Quarters | I16: Recent Results: Declining Operating Profit Margin and Net Profits (YoY)
A17: Annual Net Profits improving for last 2 years
A18: Book Value per share Improving for last 2 years
A19: Company with Zero Promoter Pledge
A22: Trailing P/E | B22: 31.22 | C22: 52 Week High | D22: 2856.15
A23: Trailing earnings | B23: 85.22 | C23: 52 Week Low | D23: 2180
A24: trailing price | B24: =+B22*B23 -> 2660.5684
A25: FORWARD P/e
A27: justified price | C27: =+B22*H40 -> 2329.0034
A28: justified p/e | C28: =1-0.95 -> 0.05
C29: =0.1-0.0965 -> 0.0035 | D29: =+C28/C29 -> 14.285714
A30: Industry | E30: 27
A31: valuation based on industry median | E31: =$E$30*H40 -> 2014.1926 | F31: =$E$30*I40 -> 2646.2622 | G31: =$E$30*J40 -> 3114.2546 | H31: =$E$30*K40 -> 3694.8158 | I31: =$E$30*L40 -> 4418.0743
A32: Expected valuation ratios based on current priceIn relation to current price
A33: Valuation Ratios | B33: Mar-18 | C33: Mar-19 | D33: Mar-20 | E33: Mar-21 | F33: Mar-22 | G33: Mar-23 | H33: Mar-24 | I33: Mar-25 | J33: Mar-26 | K33: Mar-27
A34: P/E (x) | B34: 14.35 | C34: 20.21 | D34: 17.49 | E34: 26.23 | F34: 28.64 | G34: =$B$24/H40 -> 35.664587 | H34: =$B$24/I40 -> 27.145967 | I34: =$B$24/J40 -> 23.066626 | J34: =$B$24/K40 -> 19.4422 | K34: =$B$24/L40 -> 16.259425
A35: P/B (x) | B35: 1.78 | C35: 2.09 | D35: 1.57 | E35: 1.84 | F35: 2.29 | G35: =$B$24/H51 -> 1.817283 | H35: =$B$24/I51 -> 1.6263375 | I35: =$B$24/J51 -> 1.4563702 | J35: =$B$24/K51 -> 1.3045649 | K35: =$B$24/L51 -> 1.1669307
A36: EV/EBITDA (x) | B36: 9.49 | C36: 11.64 | D36: 9.57 | E36: 16.45 | F36: 16.92 | G36: =H69/H63 -> 17.584686 | H36: =I69/I63 -> 14.597832 | I36: =J69/J63 -> 12.866356 | J36: =K69/K63 -> 11.244207 | K36: =L69/L63 -> 9.7451242
A37: P/S (x) | B37: 1.33 | C37: 1.42 | D37: 1.18 | E37: 2.77 | F37: 2.55 | G37: =$B$24/H56 -> 2.1582789 | H37: =$B$24/I56 -> 1.8839599 | I37: =$B$24/J56 -> 1.6393976 | J37: =$B$24/K56 -> 1.4220226 | K37: =$B$24/L56 -> 1.2294388
A38: Since valuation ratios are falling and earning,bookvalue and sales are rising there price seems to be overpriced
A39: particulars | B39: Column1 | C39: Column2 | D39: Column3 | E39: Column4 | F39: EXPECTED figures | G39: Column5 | H39: 2022-23E | I39: 2023-24E | J39: 2024-25E | K39: 2025-26E | L39: 2026-27E | M39: average price
A40: EPS | H40: =profitloss!G46 -> 74.599725 | I40: =profitloss!H46 -> 98.009711 | J40: =profitloss!I46 -> 115.34276 | K40: =profitloss!J46 -> 136.84503 | L40: =profitloss!K46 -> 163.63238
A41: MPS | H41: =2621 -> 2621 | I41: =2621 -> 2621 | J41: =2621 -> 2621 | K41: =2621 -> 2621 | L41: =2621 -> 2621
A42: =A25 -> FORWARD P/e | H42: =H41/H40 -> 35.134178 | I42: =I41/I40 -> 26.742248 | J42: =J41/J40 -> 22.723575 | K42: =K41/K40 -> 19.153052 | L42: =L41/L40 -> 16.017612
F43: 27 | H43: =$F$43*H40 -> 2014.1926 | I43: =$F$43*I40 -> 2646.2622 | J43: =$F$43*J40 -> 3114.2546 | K43: =$F$43*K40 -> 3694.8158 | L43: =$F$43*L40 -> 4418.0743
H44: =-PV(14%,1,0,H43,0) -> 1766.8356 | I44: =-PV(14%,2,0,I43,0) -> 2036.2128 | J44: =-PV(14%,3,0,J43,0) -> 2102.0332 | K44: =-PV(14%,4,0,K43,0) -> 2187.6275 | L44: =-PV(14%,5,0,L43,0) -> 2294.6094 | M44: =AVERAGE(H44:L44) -> 2077.4637
A46: =balancesheet!A32 -> Equity Share Capital | G46: =balancesheet!F32 -> 6765 | H46: =balancesheet!G32 -> 6765 | I46: =balancesheet!H32 -> 6765 | J46: =balancesheet!I32 -> 6765 | K46: =balancesheet!J32 -> 6765 | L46: =balancesheet!K32 -> 6765
A47: =balancesheet!A33 -> Other Equity | G47: =balancesheet!F33 -> 772720 | H47: =balancesheet!G33 -> 864012.95 | I47: =balancesheet!H33 -> 968668.19 | J47: =balancesheet!I33 -> 1084911.4 | K47: =balancesheet!J33 -> 1214341.2 | L47: =balancesheet!K33 -> 1360794.9 | N47: Company Name | O47: Price | P47: % Chg | Q47: MCap(Cr) | R47: TTM PE | S47: P/B | T47: ROE(%) | U47: 1 Yr Perform(%) | V47: Net Profit(Rs.) | W47: Net Sales(Rs.) | X47: Debt to Equity
A48: =balancesheet!A34 -> Non-Controlling Interest | G48: =balancesheet!F34 -> 109499 | H48: =balancesheet!G34 -> 119642.66 | I48: =balancesheet!H34 -> 131271.02 | J48: =balancesheet!I34 -> 144186.94 | K48: =balancesheet!J34 -> 158568.02 | L48: =balancesheet!K34 -> 174840.65 | N48: Reliance | O48: 2621.8 | P48: 0.87 | Q48: 1773826.6 | R48: 26.73 | S48: 2.09 | T48: 7.78 | U48: 15.13 | V48: 67565 | W48: 699962 | X48: 0.34
G49: =SUM(G46:G48) -> 888984 | H49: =SUM(H46:H48) -> 990420.61 | I49: =SUM(I46:I48) -> 1106704.2 | J49: =SUM(J46:J48) -> 1235863.4 | K49: =SUM(K46:K48) -> 1379674.2 | L49: =SUM(L46:L48) -> 1542400.5 | N49: ONGC | O49: 145.85 | P49: 0.03 | Q49: 183483.37 | R49: 4.49 | S49: 0.9 | T49: 17.54 | U49: 8.84 | V49: 47830 | W49: 491269 | X49: 0.42
A50: NO OF SHARES | G50: =676.5 -> 676.5 | H50: =676.5 -> 676.5 | I50: =676.5 -> 676.5 | J50: =676.5 -> 676.5 | K50: =676.5 -> 676.5 | L50: =676.5 -> 676.5 | N50: Petronet LNG | O50: 213.05 | P50: -0.02 | Q50: 31957.5 | R50: 9.23 | S50: 2.34 | T50: 25.15 | U50: 0.64 | V50: 3339 | W50: 43168 | X50: 0
A51: BVPS | G51: =+G49/G50 -> 1314.0931 | H51: =+H49/H50 -> 1464.0364 | I51: =+I49/I50 -> 1635.9264 | J51: =+J49/J50 -> 1826.849 | K51: =+K49/K50 -> 2039.4298 | L51: =+L49/L50 -> 2279.9712 | N51: Oil India | O51: 210.1 | P51: -0.78 | Q51: 22783.35 | R51: 2.81 | S51: 0.69 | T51: 18.39 | U51: 21.87 | V51: 6607 | W51: 25905 | X51: 0.54
A52: todays price | H52: =Table36[[#This Row],[EXPECTED figures]]*H51 -> #VALUE! | I52: =Table36[[#This Row],[EXPECTED figures]]*I51 -> #VALUE! | J52: =Table36[[#This Row],[EXPECTED figures]]*J51 -> #VALUE! | K52: =Table36[[#This Row],[EXPECTED figures]]*K51 -> #VALUE! | L52: =Table36[[#This Row],[EXPECTED figures]]*L51 -> #VALUE! | N52: HOEC | O52: 140.95 | P52: 0.14 | Q52: 1863.97 | R52: 44.32 | S52: 2.47 | T52: 2.65 | U52: -15.5 | V52: 20 | W52: 155 | X52: 0.47
H53: =-PV(14%,1,0,H52,0) -> #VALUE! | I53: =-PV(14%,2,0,I52,0) -> #VALUE! | J53: =-PV(14%,3,0,J52,0) -> #VALUE! | K53: =-PV(14%,4,0,K52,0) -> #VALUE! | L53: =-PV(14%,5,0,L52,0) -> #VALUE! | M53: =AVERAGE(H53:L53) -> #VALUE!
A55: Sales | G55: =profitloss!F7 -> 721634 | H55: =profitloss!G7 -> 833939.73 | I55: =profitloss!H7 -> 955367.74 | J55: =profitloss!I7 -> 1097887.7 | K55: =profitloss!J7 -> 1265714.5 | L55: =profitloss!K7 -> 1463980.6
A56: sales per share | H56: =H55/H50 -> 1232.7269 | I56: =I55/I50 -> 1412.2213 | J56: =J55/J50 -> 1622.8939 | K56: =K55/K50 -> 1870.9748 | L56: =L55/L50 -> 2164.0511
F57: 2.66 | H57: =Table36[[#This Row],[EXPECTED figures]]*H56 -> 3279.0535 | I57: =Table36[[#This Row],[EXPECTED figures]]*I56 -> 3756.5088 | J57: =Table36[[#This Row],[EXPECTED figures]]*J56 -> 4316.8978 | K57: =Table36[[#This Row],[EXPECTED figures]]*K56 -> 4976.793 | L57: =Table36[[#This Row],[EXPECTED figures]]*L56 -> 5756.376
A58: EBITD | H58: =-PV(14%,1,0,H57,0) -> 2876.3627 | I58: =-PV(14%,2,0,I57,0) -> 2890.5115 | J58: =-PV(14%,3,0,J57,0) -> 2913.783 | K58: =-PV(14%,4,0,K57,0) -> 2946.661 | L58: =-PV(14%,5,0,L57,0) -> 2989.6813 | M58: =AVERAGE(H58:L58) -> 2923.3999
A60: Profit before tax | D60: =profitloss!C24 -> 55,227 | E60: =profitloss!D24 -> 53606 | F60: =profitloss!E24 -> 55461 | G60: =profitloss!F24 -> 84142 | H60: =profitloss!G24 -> 74765.502 | I60: =profitloss!H24 -> 98227.51 | J60: =profitloss!I24 -> 115599.08 | K60: =profitloss!J24 -> 137149.13 | L60: =profitloss!K24 -> 163996.01
A61: add interest | D61: =profitloss!C16 -> 16495 | E61: =profitloss!D16 -> 22027 | F61: =profitloss!E16 -> 21189 | G61: =profitloss!F16 -> 14584 | H61: =profitloss!G16 -> 21032.867 | I61: =profitloss!H16 -> 23300.255 | J61: =profitloss!I16 -> 26097.979 | K61: =profitloss!J16 -> 29420.893 | L61: =profitloss!K16 -> 33348.725
A62: add depreciation | D62: =profitloss!C17 -> 20934 | E62: =profitloss!D17 -> 22203 | F62: =profitloss!E17 -> 26572 | G62: =profitloss!F17 -> 29797 | H62: =profitloss!G17 -> 35113.252 | I62: =profitloss!H17 -> 36394.962 | J62: =profitloss!I17 -> 38187.399 | K62: =profitloss!J17 -> 40502.862 | L62: =profitloss!K17 -> 43377.203
A63: ebitda | D63: =SUM(D60:D62) -> 37429 | E63: =SUM(E60:E62) -> 97836 | F63: =SUM(F60:F62) -> 103222 | G63: =SUM(G60:G62) -> 128523 | H63: =SUM(H60:H62) -> 130911.62 | I63: =SUM(I60:I62) -> 157922.73 | J63: =SUM(J60:J62) -> 179884.46 | K63: =SUM(K60:K62) -> 207072.88 | L63: =SUM(L60:L62) -> 240721.94
A65: Enterprise value
A66: market value of company | G66: 1773826 | H66: =1773826*(1+$G$87) -> 2075376.4 | I66: =1773826*(1+$G$87) -> 2075376.4 | J66: =1773826*(1+$G$87) -> 2075376.4 | K66: =1773826*(1+$G$87) -> 2075376.4 | L66: =1773826*(1+$G$87) -> 2075376.4
A67: debt value | D67: =debt!B7 -> 236913 | E67: =debt!C7 -> 235739 | F67: =debt!D7 -> 204586 | G67: =debt!E7 -> 250522 | H67: =debt!B38 -> 275299.67 | I67: =debt!C38 -> 307206.69 | J67: =debt!D38 -> 345242.78 | K67: =debt!E38 -> 390279.55 | L67: =debt!F38 -> 443438.57
A68: cash & cash equivalents | D68: =balancesheet!C23 -> 11081 | E68: =balancesheet!D23 -> 30920 | F68: =balancesheet!E23 -> 17397 | G68: =balancesheet!F23 -> 36178 | H68: =balancesheet!G23 -> 48636.369 | I68: =balancesheet!H23 -> 77253.761 | J68: =balancesheet!I23 -> 106161.69 | K68: =balancesheet!J23 -> 137285.52 | L68: =balancesheet!K23 -> 172949.81
A69: =A65 -> Enterprise value | D69: =D66+D67-D68 -> 225832 | E69: =E66+E67-E68 -> 204819 | F69: =F66+F67-F68 -> 187189 | G69: =G66+G67-G68 -> 1988170 | H69: =H66+H67-H68 -> 2302039.7 | I69: =I66+I67-I68 -> 2305329.4 | J69: =J66+J67-J68 -> 2314457.5 | K69: =K66+K67-K68 -> 2328370.5 | L69: =L66+L67-L68 -> 2345865.2
A72: particulars | B72: Column1 | C72: Column2 | D72: Column3 | E72: Column4 | F72: Column5 | G72: 2021-22 | H72: 2022-23E | I72: 2023-24E
A73: =A69 -> Enterprise value | G73: =G69 -> 1988170 | H73: =H69 -> 2302039.7 | I73: =I69 -> 2305329.4
A74: less debt | G74: =G67 -> 250522 | H74: =H67 -> 275299.67 | I74: =I67 -> 307206.69
A75: enterprise equity calue | G75: =+G73-G74 -> 1737648 | H75: =+H73-H74 -> 2026740.1 | I75: =+I73-I74 -> 1998122.7
A76: no of shares | G76: 676.5 | H76: 676.5 | I76: 676.5
A77: target price | G77: =+G75/G76 -> 2568.5854 | H77: =+H75/H76 -> 2995.9203 | I77: =+I75/I76 -> 2953.6181
A78: buying price | H78: =-PV(14%,1,0,H77,0) -> 2628.0002 | I78: =-PV(14%,2,0,I77,0) -> 2272.7132
A81: analysis | B81: Column1 | C81: Column2 | D81: 2018-19 | E81: 2019-20 | F81: 2020-21 | G81: 2021-22
A82: MPS | D82: 1357 | E82: 1067 | F82: =2050 -> 2050 | G82: 2615
A83: share capital | D83: =balancesheet!C32 -> 5926 | E83: =balancesheet!D32 -> 6339 | F83: =balancesheet!E32 -> 6445 | G83: =balancesheet!F32 -> 6765
A84: no of shares | D84: =+D83/10 -> 592.6 | E84: =+E83/10 -> 633.9 | F84: =+F83/10 -> 644.5 | G84: =+G83/10 -> 676.5
A85: market capitalisation | D85: =+D84*D82 -> 804158.2 | E85: =+E84*E82 -> 676371.3 | F85: =+F84*F82 -> 1321225 | G85: =+G84*G82 -> 1769047.5
E86: =+E85/D85-1 -> -0.15890766 | F86: =+F85/E85-1 -> 0.95340193 | G86: =+G85/F85-1 -> 0.33894492
G87: 0.17
A92: Return Ratios | B92: 43160 | C92: 43525 | D92: 43891 | E92: 44256 | F92: 44621 | G92: 44986 | H92: 45352 | I92: 45717 | J92: 46082 | K92: 46447
A93: Return on Networth / Equity (%) | B93: 12.29 | C93: 10.22 | D93: 8.76 | E93: 7.01 | F93: 7.78 | G93: =profitloss!G35/(balancesheet!G32+balancesheet!G33+balancesheet!G34+balancesheet!G38+balancesheet!G39+balancesheet!G41) -> 0.088825875 | H93: =profitloss!H35/(balancesheet!H32+balancesheet!H33+balancesheet!H34+balancesheet!H38+balancesheet!H39+balancesheet!H41) -> 0.090861562 | I93: =profitloss!I35/(balancesheet!I32+balancesheet!I33+balancesheet!I34+balancesheet!I38+balancesheet!I39+balancesheet!I41) -> 0.089988802 | J93: =profitloss!J35/(balancesheet!J32+balancesheet!J33+balancesheet!J34+balancesheet!J38+balancesheet!J39+balancesheet!J41) -> 0.089273141 | K93: =profitloss!K35/(balancesheet!K32+balancesheet!K33+balancesheet!K34+balancesheet!K38+balancesheet!K39+balancesheet!K41) -> 0.089820563
A94: ROCE (%) | B94: 11.42 | C94: 10.45 | D94: 10.62 | E94: 6.75 | F94: 8.02 | G94: =profitloss!G35/(balancesheet!G32+balancesheet!G33+balancesheet!G34) -> 0.11012657 | H94: =profitloss!H35/(balancesheet!H32+balancesheet!H33+balancesheet!H34) -> 0.11298062 | I94: =profitloss!I35/(balancesheet!I32+balancesheet!I33+balancesheet!I34) -> 0.11237554 | J94: =profitloss!J35/(balancesheet!J32+balancesheet!J33+balancesheet!J34) -> 0.11208106 | K94: =profitloss!K35/(balancesheet!K32+balancesheet!K33+balancesheet!K34) -> 0.11344298
A95: Return On Assets (%) | B95: 4.41 | C95: 3.94 | D95: 3.37 | E95: 3.71 | F95: 4.04 | G95: =profitloss!G35/balancesheet!G29 -> 0.066855737 | H95: =profitloss!H35/balancesheet!H29 -> 0.069184063 | I95: =profitloss!I35/balancesheet!I29 -> 0.069363199 | J95: =profitloss!J35/balancesheet!J29 -> 0.069464613 | K95: =profitloss!K35/balancesheet!K29 -> 0.070492189

Sheet balancesheet
A1: Reliance Industries LTD Balancesheet
A2: Particulars | B2: Notes | C2: As at 31st March, 2019 | D2: 31st March, 2020 | E2: As at 31st March, 2021 | F2: As at 31st March, 2022 | G2: As at 31st March, 2023 | H2: As at 31st March, 2024 | I2: As at 31st March, 2025 | J2: As at 31st March, 2026 | K2: As at 31st March, 2027
A3: ASSETS
A4: NON-CURRENT ASSETS
A5: Property, Plant and Equipment | B5: 1 | C5: 302115 | D5: 435920 | E5: 451066 | F5: 500454 | G5: =SUM(PPE!H79:H80) -> 542938.66 | H5: =SUM(PPE!I79:I80) -> 562757.09 | I5: =SUM(PPE!J79:J80) -> 590472.66 | J5: =SUM(PPE!K79:K80) -> 626275.51 | K5: =SUM(PPE!L79:L80) -> 670720
A6: Capital Work-in-Progress | B6: 1 | C6: 150178 | D6: 59096 | E6: 71171 | F6: 68052 | G6: 70620 | H6: =70620+13530 -> 84150 | I6: 84150 | J6: 100620 | K6: 100620
A7: Goodwill | C7: 11997 | D7: 10259 | E7: 10212 | F7: 13009 | G7: 13009 | H7: 13009 | I7: 13009 | J7: 13009 | K7: 13009
A8: Other Intangible Assets | B8: 1 | C8: 84262 | D8: 86479 | E8: 79980 | F8: 114335 | G8: =PPE!H81 -> 75054.576 | H8: =PPE!I81 -> 77794.23 | I8: =PPE!J81 -> 81625.566 | J8: =PPE!K81 -> 86574.868 | K8: =PPE!L81 -> 92718.771
A9: Intangible Assets Under Development | B9: 1 | C9: 29285 | D9: 50010 | E9: 54782 | F9: 104454 | G9: =105450-21620-6.88 -> 83823.12 | H9: 105450 | I9: =105450+24871 -> 130321 | J9: 105450 | K9: 105450
A10: Total PPE | C10: =SUBTOTAL(109,C3:C9) -> 577837 | D10: =SUBTOTAL(109,D3:D9) -> 641764 | E10: =SUBTOTAL(109,E3:E9) -> 667211 | F10: =SUBTOTAL(109,F3:F9) -> 800304 | G10: =SUM(G5:G9) -> 785445.35 | H10: =SUM(H5:H9) -> 843160.32 | I10: =SUM(I5:I9) -> 899578.23 | J10: =SUM(J5:J9) -> 931929.38 | K10: =SUM(K5:K9) -> 982517.77
A11: Financial Assets
A12: Investments | B12: 2 | C12: 164612 | D12: 203852 | E12: 212382 | F12: 286146 | G12: =debt!J29 -> 396372.7 | H12: =debt!K29 -> 463415.74 | I12: =debt!L29 -> 546641.79 | J12: =debt!M29 -> 645125.85 | K12: =debt!N29 -> 764000.31
A13: Loans | B13: 3 | C13: 5452 | D13: 21732 | E13: 1117 | F13: 1588 | G13: =F13 -> 1588 | H13: =G13 -> 1588 | I13: =H13 -> 1588 | J13: =I13 -> 1588 | K13: =J13 -> 1588
A14: Other Financial Assets | B14: 4 | E14: 1367 | F14: 2377 | G14: =F14 -> 2377 | H14: =G14 -> 2377 | I14: =H14 -> 2377 | J14: =I14 -> 2377 | K14: =J14 -> 2377
A15: Deferred Tax Assets (Net) | B15: 4 | C15: 4776 | D15: 2900 | E15: 1147 | F15: 1043 | G15: 1260 | H15: 1260 | I15: 1260 | J15: 1260 | K15: 1260
A16: Other Non-Current Assets | B16: 5 | C16: 17676 | D16: 37407 | E16: 64977 | F16: 61188 | G16: 62000 | H16: 62000 | I16: 62000 | J16: 92856 | K16: 107114.32
A17: Total Non-Current Assets | C17: 770353 | D17: 907655 | E17: 948201 | F17: 1152646 | G17: =SUM(G10:G16) -> 1249043.1 | H17: =SUM(H10:H16) -> 1373801.1 | I17: =SUM(I10:I16) -> 1513445 | J17: =SUM(J10:J16) -> 1675136.2 | K17: =SUM(K10:K16) -> 1858857.4
A18: CURRENT ASSETS
A19: Inventories | B19: 6 | C19: 67561 | D19: 73903 | E19: 81672 | F19: 107778 | G19: ='WORKING CAPITAL'!G8 -> 120073.6 | H19: ='WORKING CAPITAL'!H8 -> 137557.24 | I19: ='WORKING CAPITAL'!I8 -> 158077.77 | J19: ='WORKING CAPITAL'!J8 -> 182242.06 | K19: ='WORKING CAPITAL'!K8 -> 210789.12
A20: Financial Assets
A21: Investments | B21: 7 | C21: 71023 | D21: 72915 | E21: 152446 | F21: 108118 | G21: 108118 | H21: 108118 | I21: 108118 | J21: 108118 | K21: 108118
A22: Trade Receivables | B22: 8 | C22: 30089 | D22: 19656 | E22: 19014 | F22: 23640 | G22: ='WORKING CAPITAL'!G20 -> 34271.496 | H22: ='WORKING CAPITAL'!H20 -> 39261.688 | I22: ='WORKING CAPITAL'!I20 -> 45118.674 | J22: ='WORKING CAPITAL'!J20 -> 52015.662 | K22: ='WORKING CAPITAL'!K20 -> 60163.586
A23: Cash and Cash Equivalents | B23: 9 | C23: 11081 | D23: 30920 | E23: 17397 | F23: 36178 | G23: =cashflow!J53 -> 48636.369 | H23: =cashflow!K53 -> 77253.761 | I23: =cashflow!L53 -> 106161.69 | J23: =cashflow!M53 -> 137285.52 | K23: =cashflow!N53 -> 172949.81
A24: Loans | C24: 545 | D24: 669 | E24: 65 | F24: 130 | G24: 130 | H24: 130 | I24: 130 | J24: 130 | K24: 130
A25: Other Financial Assets | B25: 10 | C25: 10283 | D25: 27434 | E25: 61124 | F25: 23896 | G25: 23896 | H25: 23896 | I25: 23896 | J25: 23896 | K25: 23896
A26: Other Current Assets | B26: 11 | C26: 36804 | D26: 32763 | E26: 41293 | F26: 47279 | G26: 47279 | H26: 47279 | I26: 47279 | J26: 47279 | K26: 47279
A27: Total Current Assets | C27: 227386 | D27: 258260 | E27: 373011 | F27: 347019 | G27: =SUM(G19:G26) -> 382404.47 | H27: =SUM(H19:H26) -> 433495.69 | I27: =SUM(I19:I26) -> 488781.13 | J27: =SUM(J19:J26) -> 550966.23 | K27: =SUM(K19:K26) -> 623325.52
A28: Assets Held for Sale | B28: 39 | C28: 4667
A29: Total Assets | C29: 1002406 | D29: 1165915 | E29: 1321212 | F29: 1499665 | G29: =+G27+G17 -> 1631447.5 | H29: =+H27+H17 -> 1807296.7 | I29: =+I27+I17 -> 2002226.1 | J29: =+J27+J17 -> 2226102.5 | K29: =+K27+K17 -> 2482182.9
A30: EQUITY AND LIABILITIES
A31: EQUITY
A32: Equity Share Capital | B32: 13 | C32: 5926 | D32: 6339 | E32: 6445 | F32: 6765 | G32: =F32 -> 6765 | H32: =G32 -> 6765 | I32: =H32 -> 6765 | J32: =I32 -> 6765 | K32: =J32 -> 6765
A33: Other Equity | B33: 14 | C33: 381186 | D33: 442827 | E33: 693727 | F33: 772720 | G33: ='other equity'!F40 -> 864012.95 | H33: ='other equity'!G40 -> 968668.19 | I33: ='other equity'!H40 -> 1084911.4 | J33: ='other equity'!I40 -> 1214341.2 | K33: ='other equity'!J40 -> 1360794.9
A34: Non-Controlling Interest | C34: 8280 | D34: 12181 | E34: 99260 | F34: 109499 | G34: ='other equity'!F52 -> 119642.66 | H34: ='other equity'!G52 -> 131271.02 | I34: ='other equity'!H52 -> 144186.94 | J34: ='other equity'!I52 -> 158568.02 | K34: ='other equity'!J52 -> 174840.65
A35: LIABILITIES
A36: Non-Current Liabilities
A37: Financial Liabilities
A38: Borrowings | B38: 15 | C38: 207506 | D38: 197631 | E38: 163683 | F38: 187699 | G38: =debt!B45 -> 212474.67 | H38: =debt!C45 -> 244381.69 | I38: =debt!D45 -> 282417.78 | J38: =debt!E45 -> 327454.55 | K38: =debt!F45 -> 380613.57
A39: Other Financial Liabilities | B39: 16 | C39: 10020 | D39: 18804 | E39: 6948 | F39: 13007 | G39: =debt!B42 -> 13000 | H39: =debt!C42 -> 13000 | I39: =debt!D42 -> 13000 | J39: =debt!E42 -> 13000 | K39: =debt!F42 -> 13000
A40: Deferred Payment Liabilities | B40: 17 | C40: 18839 | D40: 18839 | E40: 18837 | F40: 37184 | G40: =debt!B44 -> 37184 | H40: =debt!C44 -> 37184 | I40: =debt!D44 -> 37184 | J40: =debt!E44 -> 37184 | K40: =debt!F44 -> 37184
A41: oyher financial liablities | E41: 14616 | F41: 12024 | G41: =debt!B43 -> 12031 | H41: =debt!C43 -> 12031 | I41: =debt!D43 -> 12031 | J41: =debt!E43 -> 12031 | K41: =debt!F43 -> 12031
A42: Provisions | B42: 18 | C42: 2856 | D42: 1790 | E42: 2625 | F42: 1853 | G42: =AVERAGE(E42:F42) -> 2239 | H42: =AVERAGE(F42:G42) -> 2046 | I42: =AVERAGE(G42:H42) -> 2142.5 | J42: =AVERAGE(H42:I42) -> 2094.25 | K42: =AVERAGE(I42:J42) -> 2118.375
A43: Deferred Tax Liabilities (Net) | B43: 4 | C43: 49923 | D43: 54123 | E43: 37001 | F43: 49644 | G43: =AVERAGE(E43:F43) -> 43322.5 | H43: =AVERAGE(F43:G43) -> 46483.25 | I43: =AVERAGE(G43:H43) -> 44902.875 | J43: =AVERAGE(H43:I43) -> 45693.062 | K43: =AVERAGE(I43:J43) -> 45297.969
A44: Other Non-Current Liabilities | C44: 548 | D44: 465 | E44: 502 | F44: 608 | G44: 610 | H44: 610 | I44: 610 | J44: 610 | K44: 610
A45: Total Non-Current Liabilities | C45: 289692 | D45: 291652 | E45: 244212 | F45: 302019 | G45: =SUM(G38:G44) -> 320861.17 | H45: =SUM(H38:H44) -> 355735.94 | I45: =SUM(I38:I44) -> 392288.16 | J45: =SUM(J38:J44) -> 438066.86 | K45: =SUM(K38:K44) -> 490854.91
A46: Current Liabilities
A47: Financial Liabilities
A48: Borrowings | B48: 19 | C48: 64436 | D48: 93786 | E48: 88128 | F48: 78606 | G48: 78606 | H48: 78606 | I48: 78606 | J48: 78606 | K48: 78606
A49: Lease liablity | E49: 1366 | F49: 2662 | G49: 2662 | H49: 2662 | I49: 2662 | J49: 2662 | K49: 2662
A50: Trade Payables | C50: 108309 | D50: 96799 | E50: 108897 | F50: 159330 | G50: ='WORKING CAPITAL'!G13 -> 170549.74 | H50: ='WORKING CAPITAL'!H13 -> 195383.09 | I50: ='WORKING CAPITAL'!I13 -> 224529.97 | J50: ='WORKING CAPITAL'!J13 -> 258852.36 | K50: ='WORKING CAPITAL'!K13 -> 299399.94
A51: Other Financial Liabilities | B51: 20 | C51: 87051 | D51: 144778 | E51: 43639 | F51: 44544 | G51: 44544 | H51: 44544 | I51: 44544 | J51: 44544 | K51: 44544
A52: Other Current Liabilities | B52: 21 | C52: 52901 | D52: 75663 | E52: 33034 | F52: 21584 | G52: 21584 | H52: 21584 | I52: 21584 | J52: 21584 | K52: 21584
A53: Provisions | B53: 22 | C53: 1326 | D53: 1890 | E53: 2504 | F53: 1936 | G53: =AVERAGE(E53:F53) -> 2220 | H53: =AVERAGE(F53:G53) -> 2078 | I53: =AVERAGE(G53:H53) -> 2149 | J53: =AVERAGE(H53:I53) -> 2113.5 | K53: =AVERAGE(I53:J53) -> 2131.25
A54: Total Current Liabilities | C54: 314023 | D54: 412916 | E54: 277568 | F54: 308662 | G54: =SUM(G48:G53) -> 320165.74 | H54: =SUM(H48:H53) -> 344857.09 | I54: =SUM(I48:I53) -> 374074.97 | J54: =SUM(J48:J53) -> 408361.86 | K54: =SUM(K48:K53) -> 448927.19
A55: Liabilities directly associated with Assets Held for Sale | B55: 39 | C55: 3299
A56: Total Liabilities | C56: 607014 | D56: 704568 | E56: 521780 | F56: 610681 | G56: =+G54+G45 -> 641026.91 | H56: =+H54+H45 -> 700593.03 | I56: =+I54+I45 -> 766363.13 | J56: =+J54+J45 -> 846428.72 | K56: =+K54+K45 -> 939782.1
A57: Total Equity and Liabilities | C57: 1002406 | D57: 1165915 | E57: 1321212 | F57: 1499665 | G57: =+G56+G32+G33+G34 -> 1631447.5 | H57: =+H56+H32+H33+H34 -> 1807297.2 | I57: =+I56+I32+I33+I34 -> 2002226.5 | J57: =+J56+J32+J33+J34 -> 2226103 | K57: =+K56+K32+K33+K34 -> 2482182.6
A58: Significant Accounting Policies
A59: See accompanying Notes to the Financial Statements | B59: 1 to 42
A63: balancing fig is adjusted in capital workin progress other non current assset

Sheet profitloss
A1: PROFIT/LOSS | B1: Notes | C1: 2018-19 | D1: 2019-20 | E1: 2020-21 | F1: 2021-22 | G1: =Table18[[#Headers],[2022-23E]] -> 2022-23E | H1: =Table18[[#Headers],[2023-24E]] -> 2023-24E | I1: =Table18[[#Headers],[2024-25E]] -> 2024-25E | J1: =Table18[[#Headers],[2025-26E]] -> 2025-26E | K1: =Table18[[#Headers],[2026-27E]] -> 2026-27E
A2: INCOME
A3: Value of Sales | C3: 5,85,540 | D3: 591778 | E3: 467669 | F3: 696972
A4: Income from Services | C4: 39,672 | D4: 68219 | E4: 71569 | F4: 95784
A5: Value of Sales & Services (Revenue) | C5: 625212 | D5: 659997 | E5: 539238 | F5: 792756
A6: Less: GST Recovered | C6: 42,118 | D6: 47560 | E6: 52912 | F6: 71122
A7: REVENUE FROM OPERATIONS | B7: 23 | C7: 583094 | D7: 612437 | E7: 486326 | F7: 721634 | G7: =Table18[[#Totals],[2022-23E]] -> 833939.73 | H7: =Table18[[#Totals],[2023-24E]] -> 955367.74 | I7: =Table18[[#Totals],[2024-25E]] -> 1097887.7 | J7: =Table18[[#Totals],[2025-26E]] -> 1265714.5 | K7: =Table18[[#Totals],[2026-27E]] -> 1463980.6
A8: Other Income | B8: 24 | C8: 8386 | D8: 13164 | E8: 16327 | F8: 14947 | G8: =revenue!C96 -> 12350 | H8: =revenue!D96 -> 12350 | I8: =revenue!E96 -> 12350 | J8: =revenue!F96 -> 12350 | K8: =revenue!G96 -> 12350
A9: Total Income | C9: 591480 | D9: 625601 | E9: 502653 | F9: 736581 | G9: =SUM(G7:G8) -> 846289.73 | H9: =SUM(H7:H8) -> 967717.74 | I9: =SUM(I7:I8) -> 1110237.7 | J9: =SUM(J7:J8) -> 1278064.5 | K9: =SUM(K7:K8) -> 1476330.6
A10: EXPENSES
A11: Cost of Material Consumed | C11: 275237 | D11: 260621 | E11: 199915 | F11: 360784 | G11: =expenses!H5 -> 375272.88 | H11: =expenses!I5 -> 429915.48 | I11: =expenses!J5 -> 494049.48 | J11: =expenses!K5 -> 569571.5 | K11: =expenses!L5 -> 658791.27
A12: Purchase of Stock-in-Trade | C12: 123930 | D12: 149667 | E12: 101850 | F12: 135585 | G12: =expenses!H7 -> 183466.74 | H12: =expenses!I7 -> 210180.9 | I12: =expenses!J7 -> 241535.3 | J12: =expenses!K7 -> 278457.18 | K12: =expenses!L7 -> 322075.73
A13: Changes in Inventories of Finished Goods, Work-in-Progress and Stock-in-Trade | B13: 25 | C13: -4680 | D13: -5048 | E13: -9064 | F13: -21457 | G13: =+'WORKING CAPITAL'!F8-'WORKING CAPITAL'!G8 -> -12295.601 | H13: =+'WORKING CAPITAL'!G8-'WORKING CAPITAL'!H8 -> -17483.636 | I13: =+'WORKING CAPITAL'!H8-'WORKING CAPITAL'!I8 -> -20520.533 | J13: =+'WORKING CAPITAL'!I8-'WORKING CAPITAL'!J8 -> -24164.287 | K13: =+'WORKING CAPITAL'!J8-'WORKING CAPITAL'!K8 -> -28547.063
A14: Excise Duty | C14: 13885 | D14: 14902 | E14: 19402 | F14: 21672 | G14: =expenses!H11 -> 20848.493 | H14: =expenses!I11 -> 23884.194 | I14: =expenses!J11 -> 27447.193 | J14: =expenses!K11 -> 31642.861 | K14: =expenses!L11 -> 36599.515
A15: Employee Benefits Expense | B15: 26 | C15: 12488 | D15: 14075 | E15: 14817 | F15: 18775 | G15: =expenses!H13 -> 25018.192 | H15: =expenses!I13 -> 28661.032 | I15: =expenses!J13 -> 32936.632 | J15: =expenses!K13 -> 37971.434 | K15: =expenses!L13 -> 43919.418
A16: Finance Costs | B16: 27 | C16: 16495 | D16: 22027 | E16: 21189 | F16: 14584 | G16: =debt!B40 -> 21032.867 | H16: =debt!C40 -> 23300.255 | I16: =debt!D40 -> 26097.979 | J16: =debt!E40 -> 29420.893 | K16: =debt!F40 -> 33348.725
A17: Depreciation/Amortisation and Depletion Expense | B17: 1 | C17: 20934 | D17: 22203 | E17: 26572 | F17: 29797 | G17: =expenses!H15 -> 35113.252 | H17: =expenses!I15 -> 36394.962 | I17: =expenses!J15 -> 38187.399 | J17: =expenses!K15 -> 40502.862 | K17: =expenses!L15 -> 43377.203
A18: Other Expenses | B18: 28 | C18: 78067 | D18: 89211 | E18: 78669 | F18: 95815 | G18: =expenses!H16 -> 123307.41 | H18: =expenses!I16 -> 134877.04 | I18: =expenses!J16 -> 155145.2 | J18: =expenses!K16 -> 177752.88 | K18: =expenses!L16 -> 203009.79
A19: Total Expenses | C19: 5,36,356 | D19: 567658 | E19: 453350 | F19: 655555 | G19: =SUM(G11:G18) -> 771764.23 | H19: =SUM(H11:H18) -> 869730.23 | I19: =SUM(I11:I18) -> 994878.65 | J19: =SUM(J11:J18) -> 1141155.3 | K19: =SUM(K11:K18) -> 1312574.6
A20: PROFIT BEFORE SHARE OF PROFIT / (LOSS) OF ASSOCIATES AND JOINT VENTURES, EXCEPTIONAL ITEM AND TAX | C20: 55,124 | D20: 57943 | E20: 49303 | F20: 81026 | G20: =+G9-G19 -> 74525.502 | H20: =+H9-H19 -> 97987.51 | I20: =+I9-I19 -> 115359.08 | J20: =+J9-J19 -> 136909.13 | K20: =+K9-K19 -> 163756.01
A21: Share of Profit / (Loss) of Associates and Joint Ventures | C21: 103 | D21: 107 | E21: 516 | F21: 280 | G21: 240 | H21: 240 | I21: 240 | J21: 240 | K21: 240
A22: PROFIT BEFORE EXCEPTIONAL ITEM AND TAX | C22: 55,227 | D22: 58050 | E22: 49819 | F22: 81306 | G22: =+G20+G21 -> 74765.502 | H22: =+H20+H21 -> 98227.51 | I22: =+I20+I21 -> 115599.08 | J22: =+J20+J21 -> 137149.13 | K22: =+K20+K21 -> 163996.01
A23: Exceptional Item (Net of Tax) | B23: 28.2 | C23: - | D23: -4444 | E23: 5642 | F23: 2836
A24: PROFIT BEFORE TAX* | C24: 55,227 | D24: 53606 | E24: 55461 | F24: 84142 | G24: =+G22 -> 74765.502 | H24: =+H22 -> 98227.51 | I24: =+I22 -> 115599.08 | J24: =+J22 -> 137149.13 | K24: =+K22 -> 163996.01
A25: TAX EXPENSES
A26: Current Tax | B26: 12 | C26: 11683 | D26: 8630 | E26: 2205 | F26: 3161 | G26: =G24*expenses!$B$29 -> 18691.375 | H26: =H24*expenses!$B$29 -> 24556.878 | I26: =I24*expenses!$B$29 -> 28899.77 | J26: =J24*expenses!$B$29 -> 34287.282 | K26: =K24*expenses!$B$29 -> 40999.003
A27: Deferred Tax | B27: 12 | C27: 3707 | D27: 5096 | E27: -483 | F27: 13136
A28: PROFIT FOR THE YEAR | C28: 39837 | D28: 39880 | E28: 53739 | F28: 67845 | G28: =G24-G26 -> 56074.126 | H28: =H24-H26 -> 73670.633 | I28: =I24-I26 -> 86699.311 | J28: =J24-J26 -> 102861.85 | K28: =K24-K26 -> 122997.01
A29: OTHER COMPREHENSIVE INCOME
A30: i. Items that will not be reclassified to Profit or Loss | B30: 24.1 | C30: 77470 | D30: 22286 | E30: 37517 | F30: 27533 | G30: =AVERAGE(Table_0__2[[#This Row],[2018-19]],E30) -> 57493.5 | H30: 56250 | I30: =AVERAGE(G30:H30) -> 56871.75 | J30: =AVERAGE(H30:I30) -> 56560.875 | K30: =AVERAGE(I30:J30) -> 56716.312
A31: ii. Income Tax relating to items that will not be reclassified to Profit or Loss | C31: (16,705) | D31: -1088 | E31: -4605 | F31: -3215 | G31: =AVERAGE(E31:F31) -> -3910 | H31: =AVERAGE(F31:G31) -> -3562.5 | I31: =AVERAGE(G31:H31) -> -3736.25 | J31: =AVERAGE(H31:I31) -> -3649.375 | K31: =AVERAGE(I31:J31) -> -3692.8125
A32: iii. Items that will be reclassified to Profit or Loss | B32: 24.2 | C32: (2,177) | D32: -7085 | E32: 1264 | F32: -2584 | G32: =AVERAGE(E32:F32) -> -660 | H32: =AVERAGE(F32:G32) -> -1622 | I32: =AVERAGE(G32:H32) -> -1141 | J32: =AVERAGE(H32:I32) -> -1381.5 | K32: =AVERAGE(I32:J32) -> -1261.25
A33: iv. Income tax relating to items that will be reclassified to Profit or Loss | C33: 177 | D33: 1180 | E33: -378 | F33: 526 | G33: =AVERAGE(E33:F33) -> 74 | H33: =AVERAGE(F33:G33) -> 300 | I33: =AVERAGE(G33:H33) -> 187 | J33: =AVERAGE(H33:I33) -> 243.5 | K33: =AVERAGE(I33:J33) -> 215.25
A34: Total Other Comprehensive Income/(Loss) for the Year (Net of Tax) | C34: 58,765 | D34: 15293 | E34: 33798 | F34: 22260 | G34: =SUM(G30:G33) -> 52997.5 | H34: =SUM(H30:H33) -> 51365.5 | I34: =SUM(I30:I33) -> 52181.5 | J34: =SUM(J30:J33) -> 51773.5 | K34: =SUM(K30:K33) -> 51977.5
A35: Total Comprehensive Income for the Year | C35: 98,602 | D35: 55173 | E35: 87537 | F35: 90105 | G35: =G34+G28 -> 109071.63 | H35: =H34+H28 -> 125036.13 | I35: =I34+I28 -> 138880.81 | J35: =J34+J28 -> 154635.35 | K35: =K34+K28 -> 174974.51
A36: NET PROFIT ATTRIBUTABLE TO:
A37: a) Owners of the Company | C37: 39,588 | D37: 39354 | E37: 49128 | F37: 60705 | G37: =G28*0.9 -> 50466.714 | H37: =H28*0.9 -> 66303.569 | I37: =I28*0.9 -> 78029.38 | J37: =J28*0.9 -> 92575.661 | K37: =K28*0.9 -> 110697.31
A38: b) Non-Controlling Interest | C38: 249 | D38: 526 | E38: 4611 | F38: 7140 | G38: =G28*0.1 -> 5607.4126 | H38: =H28*0.1 -> 7367.0633 | I38: =I28*0.1 -> 8669.9311 | J38: =J28*0.1 -> 10286.185 | K38: =K28*0.1 -> 12299.701
A39: OTHER COMPREHENSIVE INCOME ATTRIBUTABLE TO:
A40: a) Owners of the Company | C40: 58,773 | D40: 15311 | E40: 33849 | F40: 22185 | G40: =G34*0.9 -> 47697.75 | H40: =H34*0.9 -> 46228.95 | I40: =I34*0.9 -> 46963.35 | J40: =J34*0.9 -> 46596.15 | K40: =K34*0.9 -> 46779.75
A41: b) Non-Controlling Interest | C41: (8) | D41: -18 | E41: -51 | F41: 75 | G41: =G34*0.1 -> 5299.75 | H41: =H34*0.1 -> 5136.55 | I41: =I34*0.1 -> 5218.15 | J41: =J34*0.1 -> 5177.35 | K41: =K34*0.1 -> 5197.75
A42: TOTAL COMPREHENSIVE INCOME ATTRIBUTABLE TO:
A43: a) Owners of the Company | C43: 98,361 | D43: 54665 | E43: 82977 | F43: 82890 | G43: =G35*0.9 -> 98164.464 | H43: =H35*0.9 -> 112532.52 | I43: =I35*0.9 -> 124992.73 | J43: =J35*0.9 -> 139171.81 | K43: =K35*0.9 -> 157477.06
A44: b) Non-Controlling Interest | C44: 241 | D44: 508 | E44: 4560 | F44: 7215 | G44: =G35*0.1 -> 10907.163 | H44: =H35*0.1 -> 12503.613 | I44: =I35*0.1 -> 13888.081 | J44: =J35*0.1 -> 15463.535 | K44: =K35*0.1 -> 17497.451
A45: EARNINGS PER EQUITY SHARE OF FACE VALUE OF ` 10 EACH
A46: Basic (in `) – Before Exceptional Item | B46: 29 | C46: 66.82 | D46: 63.07 | E46: 76.37 | F46: 92 | G46: =G37/$C$50 -> 74.599725 | H46: =H37/$C$50 -> 98.009711 | I46: =I37/$C$50 -> 115.34276 | J46: =J37/$C$50 -> 136.84503 | K46: =K37/$C$50 -> 163.63238
A47: Basic (in `) – After Exceptional Item | B47: 29 | C47: 66.82 | D47: 70.19 | E47: 67.6 | F47: 87.71
A48: Diluted (in `) – Before Exceptional Item | B48: 29 | C48: 66.80 | D48: 63.06 | E48: 75.21 | F48: 90.85
A49: Diluted (in `) – After Exceptional Item | B49: 29 | C49: 66.80 | D49: 70.18 | E49: 66.57 | F49: 86.61
A50: Significant Accounting Policies | C50: 676.5
A51: See accompanying Notes to the Financial Statements | B51: 1 to 42 | F51: =F47*C50 -> 59335.815
E52: =644.5 -> 644.5 | F52: =+F37/F47 -> 692.11036
A53: dividend | E53: =E37/E52 -> 76.226532 | F53: 4297 | G53: =G35*7% -> 7635.0138 | H53: =H35*7% -> 8752.5293 | I53: =I35*7% -> 9721.6568 | J53: =J35*7% -> 10824.474 | K53: =K35*7% -> 12248.216
F54: =+C50*F47 -> 59335.815
F57: =92*C50 -> 62238

Sheet cashflow
E1: 2019-20
B2: CASH FLOW | D2: 2018-19 | F2: 2019-20 | H2: 2020-21 | I2: 2021-22 | J2: =profitloss!G1 -> 2022-23E | K2: =profitloss!H1 -> 2023-24E | L2: =profitloss!I1 -> 2024-25E | M2: =profitloss!J1 -> 2025-26E | N2: =profitloss!K1 -> 2026-27E
A3: A. | B3: CASH FLOW FROM OPERATING ACTIVITIES | G3: 2020-21
B4: NET PROFIT BEFORE TAX AS PER STATEMENT OF PROFIT AND LOSS (AFTER EXCEPTIONAL ITEM AND TAX THEREON) | D4: 55,227 | E4: 53606 | F4: 53606 | G4: 55461 | H4: 55461 | I4: 84142 | J4: =profitloss!G24 -> 74765.502 | K4: =profitloss!H24 -> 98227.51 | L4: =profitloss!I24 -> 115599.08 | M4: =profitloss!J24 -> 137149.13 | N4: =profitloss!K24 -> 163996.01
B5: Adjusted for:
B6: Share of (Profit) / Loss of Associates and Joint Ventures | D6: (103) | E6: -107 | F6: -107 | G6: -516 | H6: -516 | I6: -280 | J6: =-profitloss!G21 -> -240 | K6: =-profitloss!H21 -> -240 | L6: =-profitloss!I21 -> -240 | M6: =-profitloss!J21 -> -240 | N6: =-profitloss!K21 -> -240
B7: Loss on Buy back of Debentures | D7: - | E7: 60 | F7: 60 | G7: 194 | H7: 194 | I7: 380 | J7: 0 | K7: 0 | L7: 0 | M7: 0 | N7: 0
B8: (Profit) / Loss on Sale / Discard of Property, Plant and Equipment and Other Intangible Asset (Net) | D8: 33 | E8: 247 | F8: 247 | G8: 47 | H8: 47 | I8: 40 | J8: 0 | K8: 0 | L8: 0 | M8: 0 | N8: 0
B9: Depreciation / Amortisation and Depletion Expense | D9: 20,934 | E9: 22203 | F9: 22203 | G9: 26572 | H9: 26572 | I9: 29797 | J9: =profitloss!G17 -> 35113.252 | K9: =profitloss!H17 -> 36394.962 | L9: =profitloss!I17 -> 38187.399 | M9: =profitloss!J17 -> 40502.862 | N9: =profitloss!K17 -> 43377.203
B10: Effect of Exchange Rate Change | D10: (1,319) | E10: 107 | F10: 107 | G10: -1645 | H10: -1645 | I10: 1821 | J10: 0 | K10: 0 | L10: 0 | M10: 0 | N10: 0
B11: (Profit) / Loss on Divestment of Stake | D11: (20) | E11: 11 | F11: 11 | G11: - | H11: -4964 | I11: -1352 | J11: 0 | K11: 0 | L11: 0 | M11: 0 | N11: 0
B12: Net Gain on Financial Assets# | D12: (2,471) | E12: -2076 | F12: -2064 | G12: -4964 | H12: -5642 | I12: -2836 | J12: 0 | K12: 0 | L12: 0 | M12: 0 | N12: 0
B13: Tax on Exceptional item | D13: - | E13: -948 | F13: -948 | G13: -5642 | H13: -39 | I13: -41 | J13: 0 | K13: 0 | L13: 0 | M13: 0 | N13: 0
B14: Dividend Income# | D14: (501) | E14: -110 | F14: -100 | G14: -39 | H14: -10366 | I14: -12529 | J14: =-profitloss!G8 -> -12350 | K14: =-profitloss!H8 -> -12350 | L14: =-profitloss!I8 -> -12350 | M14: =-profitloss!J8 -> -12350 | N14: =-profitloss!K8 -> -12350
B15: Interest Income# | D15: (4,952) | E15: -10317 | F15: -9548 | G15: -10366 | H15: 21027 | I15: 14584
B16: Finance Costs# | D16: 16,491 | E16: 21880 | F16: 21880 | G16: 21027 | H16: 24668 | I16: 29584 | J16: =profitloss!G16 -> 21032.867 | K16: =profitloss!H16 -> 23300.255 | L16: =profitloss!I16 -> 26097.979 | M16: =profitloss!J16 -> 29420.893 | N16: =profitloss!K16 -> 33348.725
B17: Operating Profit before Working Capital Changes | D17: 83,319 | E17: 84556 | F17: 85347 | G17: 80129 | H17: 80129 | I17: 113726 | J17: =SUM(J4:J16) -> 118321.62 | K17: =SUM(K4:K16) -> 145332.73 | L17: =SUM(L4:L16) -> 167294.46 | M17: =SUM(M4:M16) -> 194482.88 | N17: =SUM(N4:N16) -> 228131.94
B18: Adjusted for: | H18: 959 | I18: -14180
B19: Trade and Other Receivables | D19: (40,136) | E19: -9804 | F19: -13792 | G19: 186 | H19: -7769 | I19: -24983 | J19: =balancesheet!F22-balancesheet!G22 -> -10631.496 | K19: =balancesheet!G22-balancesheet!H22 -> -4990.1922 | L19: =balancesheet!H22-balancesheet!I22 -> -5856.9857 | M19: =balancesheet!I22-balancesheet!J22 -> -6896.9886 | N19: =balancesheet!J22-balancesheet!K22 -> -8147.9239
B20: Inventories | D20: (6,724) | E20: -6342 | F20: -6342 | G20: -7769 | H20: -43148 | I20: 39888 | J20: =balancesheet!F19-balancesheet!G19 -> -12295.601 | K20: =balancesheet!G19-balancesheet!H19 -> -17483.636 | L20: =balancesheet!H19-balancesheet!I19 -> -20520.533 | M20: =balancesheet!I19-balancesheet!J19 -> -24164.287 | N20: =balancesheet!J19-balancesheet!K19 -> -28547.063
B21: Trade and Other Payables | D21: 18,078 | E21: 38050 | F21: 38050 | G21: -43148 | H21: -49958 | I21: 725 | J21: =balancesheet!G50-balancesheet!F50 -> 11219.739 | K21: =balancesheet!H50-balancesheet!G50 -> 24833.348 | L21: =balancesheet!I50-balancesheet!H50 -> 29146.886 | M21: =balancesheet!J50-balancesheet!I50 -> 34322.389 | N21: =balancesheet!K50-balancesheet!J50 -> 40547.582
B22: Cash Generated from Operations | D22: 54,537 | E22: 106460 | F22: 103263 | G22: 29398 | H22: 30171 | I22: 114451 | J22: =SUM(J17:J21) -> 106614.26 | K22: =SUM(K17:K21) -> 147692.25 | L22: =SUM(L17:L21) -> 170063.83 | M22: =SUM(M17:M21) -> 197744 | N22: =SUM(N17:N21) -> 231984.53
B23: Taxes Paid (Net) | D23: (12,191) | E23: -8386 | F23: -8386 | G23: -3213 | H23: -3213 | I23: -3797 | J23: =AVERAGE(H23:I23) -> -3505 | K23: =AVERAGE(I23:J23) -> -3651 | L23: =AVERAGE(J23:K23) -> -3578 | M23: =AVERAGE(K23:L23) -> -3614.5 | N23: =AVERAGE(L23:M23) -> -3596.25
B24: Net Cash Flow from Operating Activities* | D24: 42,346 | E24: 98074 | F24: 94877 | G24: 26185 | H24: 26958 | I24: 110654 | J24: =+J22+J23 -> 103109.26 | K24: =+K22+K23 -> 144041.25 | L24: =+L22+L23 -> 166485.83 | M24: =+M22+M23 -> 194129.5 | N24: =+N22+N23 -> 228388.28
A25: B. | B25: CASH FLOW FROM INVESTING ACTIVITIES
B26: Purchase of Property, Plant and Equipment and Other Intangible Assets | D26: (93,626) | E26: -76517 | F26: -76517 | G26: -105837 | H26: -105837 | I26: -100145 | J26: =-PPE!H86 -> -38317.483 | K26: =-PPE!I86 -> -58953.053 | L26: =-PPE!J86 -> -69734.302 | M26: =-PPE!K86 -> -81255.015 | N26: =-PPE!L86 -> -93965.595
B27: Proceeds from disposal of Property, Plant and Equipment and Intangible Assets | D27: 849 | E27: 964 | F27: 964 | G27: 2319 | H27: 2319 | I27: 3137 | J27: 0 | K27: 0 | L27: 0 | M27: 0 | N27: 0
B28: Purchase of Other Investments | D28: (11,05,479) | E28: -1159270 | F28: -1156843 | G28: -689866 | H28: -689866 | I28: -667878 | J28: =-debt!B27-debt!B28 -> -60793.2 | K28: =-debt!C27-debt!C28 -> -68675.04 | L28: =-debt!D27-debt!D28 -> -82410.048 | M28: =-debt!E27-debt!E28 -> -98892.058 | N28: =-debt!F27-debt!F28 -> -118670.47
B29: Proceeds from Sale of Financial Assets (including Advance Received) | D29: 11,03,615 | E29: 1173330 | F29: 1173329 | G29: 642551 | H29: 642551 | I29: 668137
B30: Upfront Fibre Payment | D30: - | E30: -16439 | F30: -16439 | G30: -
B31: Net Cash Flow for Other Financial Assets | D31: (1,960) | E31: 650 | F31: 1467 | G31: 773 | H31: -2 | I31: -19306 | J31: =profitloss!G8 -> 12350 | K31: =profitloss!H8 -> 12350 | L31: =profitloss!I8 -> 12350 | M31: =profitloss!J8 -> 12350 | N31: =profitloss!K8 -> 12350
B32: Interest Income | D32: 972 | E32: 1477 | F32: 1441 | G32: 8400 | H32: 8400 | I32: 5933
B33: Dividend Income from Associates | D33: 3 | E33: 18 | F33: 18 | G33: 26 | H33: 26 | I33: 18
B34: Dividend Income from Others | D34: 498 | E34: 70 | F34: 60 | G34: - | H34: - | I34: 1
B35: Net Cash Flow used in Investing Activities | D35: (95,128) | E35: -75717 | F35: -72520 | G35: -141634 | H35: -142409 | I35: -110103 | J35: =SUM(J26:J34) -> -86760.683 | K35: =SUM(K26:K34) -> -115278.09 | L35: =SUM(L26:L34) -> -139794.35 | M35: =SUM(M26:M34) -> -167797.07 | N35: =SUM(N26:N34) -> -200286.06
A36: C. | B36: CASH FLOW FROM FINANCING ACTIVITIES
B37: Proceeds from Issue of Equity Share Capital | D37: 117 | E37: 18 | F37: 18 | G37: 5 | H37: 5 | I37: 5 | J37: 0 | K37: 0 | L37: 0 | M37: 0 | N37: 0
B38: Proceeds from Issue of Share Capital to Non-Controlling Interest / Compulsory Convertible Debentures | D38: 113 | E38: 111 | F38: 111 | G38: 200382 | H38: 200382 | I38: 450 | J38: 0 | K38: 0 | L38: 0 | M38: 0 | N38: 0
B39: Net Proceeds from Right Issue | F39: - | G39: 13210 | H39: 13210 | I39: 39762 | J39: 0 | K39: 0 | L39: 0 | M39: 0 | N39: 0
B40: Share Application Money | D40: 2 | E40: 1 | F40: 1 | G40: -
B41: Payment of Lease Liabilities | D41: - | E41: -1062 | F41: -1062 | G41: -1022 | H41: -1022 | I41: -2132
B42: Proceeds from Borrowings – Non-Current | D42: 80,299 | E42: 28665 | F42: 28665 | G42: 33211 | H42: 33211 | I42: 59343 | J42: =debt!B35 -> 24777.671 | K42: =debt!C35 -> 31907.023 | L42: =debt!D35 -> 38036.087 | M42: =debt!E35 -> 45036.768 | N42: =debt!F35 -> 53159.016
B43: Repayment of Borrowings – Non-Current | D43: (20,245) | E43: -18179 | F43: -18179 | G43: -87240 | H43: -87240 | I43: -40647 | J43: 0 | K43: 0 | L43: 0 | M43: 0 | N43: 0
B44: Borrowings – Current (Net) | D44: 26,402 | E44: 25095 | F44: 25095 | G44: -29681 | H44: -29681 | I44: -8846 | J44: 0 | K44: 0 | L44: 0 | M44: 0
B45: Deferred Payment Liabilities | D45: (870) | E45: -1370 | F45: -1370 | G45: -2
B46: Movement in Deposits | D46: (2,292) | E46: -2720 | F46: -2720 | G46: -4700 | H46: -4700 | I46: - | J46: 0
B47: Dividends Paid (including Dividend Distribution Tax) | D47: (4,282) | E47: -4592 | F47: -4592 | G47: -3921 | H47: -3921 | I47: -4297 | J47: =-profitloss!G53 -> -7635.0138 | K47: =-profitloss!H53 -> -8752.5293 | L47: =-profitloss!I53 -> -9721.6568 | M47: =-profitloss!J53 -> -10824.474 | N47: =-profitloss!K53 -> -12248.216
B48: Interest Paid | D48: (23,338) | E48: -28508 | F48: -28508 | G48: -18340 | H48: -18340 | I48: -26349 | J48: =-profitloss!G16 -> -21032.867 | K48: =-profitloss!H16 -> -23300.255 | L48: =-profitloss!I16 -> -26097.979 | M48: =-profitloss!J16 -> -29420.893 | N48: =-profitloss!K16 -> -33348.725
B49: Net Cash Flow (used in) / from Financing Activities | D49: 55,906 | E49: -2541 | F49: -2541 | G49: 101902 | H49: 101904 | I49: 17289 | J49: =SUM(J37:J48) -> -3890.2099 | K49: =SUM(K37:K48) -> -145.76051 | L49: =SUM(L37:L48) -> 2216.4516 | M49: =SUM(M37:M48) -> 4791.4007 | N49: =SUM(N37:N48) -> 7562.076
B50: Net Increase in Cash and Cash Equivalents | D50: 3,124 | E50: 19816 | F50: 19816 | G50: -13547 | H50: -13547 | I50: 17840 | J50: =++J24+J35+J49 -> 12458.369 | K50: =++K24+K35+K49 -> 28617.392 | L50: =++L24+L35+L49 -> 28907.929 | M50: =++M24+M35+M49 -> 31123.825 | N50: =++N24+N35+N49 -> 35664.294
B51: Opening Balance of Cash and Cash Equivalents | D51: 7,336 | E51: 11081 | F51: 11081 | G51: 30920 | H51: 30920 | I51: 17397 | J51: =I53 -> 36178 | K51: =J53 -> 48636.369 | L51: =K53 -> 77253.761 | M51: =L53 -> 106161.69 | N51: =M53 -> 137285.52
B52: Add: Upon addition of Subsidiaries | D52: 621 | E52: 23 | F52: 23 | G52: 24 | H52: 24 | I52: 941
B53: Closing Balance of Cash and Cash Equivalents (Refer Note 9) | D53: 11,081 | E53: 30920 | F53: 30920 | G53: 17397 | H53: 17397 | I53: 36178 | J53: =SUM(J50:J52) -> 48636.369 | K53: =SUM(K50:K52) -> 77253.761 | L53: =SUM(L50:L52) -> 106161.69 | M53: =SUM(M50:M52) -> 137285.52 | N53: =SUM(N50:N52) -> 172949.81

Sheet charts
B3: sales growth historical | K3: sales to expected
B24: profit after tax | K24: profit after tax
C42: eps
B43: year | C43: 2020 | D43: 2021 | E43: 2022 | F43: 2023 | G43: 2024 | H43: 2025 | I43: 2026 | J43: 2027 | M43: cash flow
B44: eps | C44: 63.07 | D44: 76.37 | E44: 92 | F44: 74.599725 | G44: 98.009711 | H44: 115.34276 | I44: 136.84503 | J44: 163.63238
B63: operating cash flow

Sheet other equity
G1: SHEET SUMMARY
G3: 1 | H3: Notes to accounts
G4: 2 | H4: summary
G5: 3 | H5: estimation
A6: B. | B6: Other Equity | S6: (` in crore)
R7: Others
B8: particulars | C8: Balance as at 1st April, 2020 | D8: Total Comprehensive Income for the Year | E8: Dividend | F8: Tax on Dividend | G8: Transfer (to)/from Retained Earnings | H8: On Employee Stock Options | I8: Others | J8: Balance as at 1st April, 20202 | K8: Total Comprehensive Income for the Year3 | L8: Column4 | M8: Transfer (to)/from Retained Earnings5 | N8: Transfer (to)/from General Reserve | O8: On Rights Issue* | P8: On Employee Stock Options | Q8: Column6 | R8: Balance as at 31st March, 2021 | S8: Balance as at 1st April, 2021 | T8: Total Comprehensive Income for the Year | U8: Dividend7 | V8: Transfer (to) / from Retained Earnings | W8: Transfer (to) / from General Reserve | X8: On Rights Issue * | Y8: On Employee Stock Options | Z8: Others8 | AA8: Balance as at 31st March, 2022
B10: As at 31^{st} March, 2021
B11: Share Application Money | J11: 1 | K11: - | L11: - | M11: - | N11: - | O11: - | P11: - | Q11: -1 | R11: -
B12: Pending Allotment
B13: Share Call Money Account | J13: - | K13: - | L13: - | M13: - | N13: - | O13: 39843 | P13: - | Q13: - | R13: 39843 | S13: 39843 | T13: - | U13: - | V13: - | W13: - | X13: -39843
B15: Reserves and Surplus
B16: Capital Reserve | C16: 291 | D16: - | E16: - | F16: - | G16: - | H16: - | I16: - | J16: 291 | K16: - | L16: - | M16: - | N16: - | O16: - | P16: - | Q16: - | R16: 291 | S16: 291 | T16: - | U16: - | V16: - | W16: - | X16: - | Y16: - | Z16: - | AA16: 291
B17: Capital Redemption Reserve | C17: 14 | D17: - | E17: - | F17: - | G17: 40 | H17: - | I17: -4 | J17: 50 | K17: - | L17: - | M17: - | N17: - | O17: - | P17: - | Q17: - | R17: 50 | S17: 50 | T17: - | U17: - | V17: - | W17: - | X17: - | Y17: - | Z17: - | AA17: 50
B18: Debenture Redemption Reserve | C18: 9412 | D18: - | E18: - | F18: - | G18: 15 | H18: - | I18: - | J18: 9427 | K18: - | L18: - | M18: -41 | N18: -3410 | O18: - | P18: - | Q18: - | R18: 5976 | S18: 5976 | T18: - | U18: - | V18: 524 | W18: -1795 | X18: - | Y18: - | Z18: - | AA18: 4705
B19: Share Based Payments Reserve | C19: 7 | D19: - | E19: - | F19: - | G19: - | H19: 11 | I19: - | J19: 18 | K19: - | L19: - | M19: - | N19: - | O19: - | P19: 719 | Q19: - | R19: 737 | S19: 737 | T19: - | U19: - | V19: - | W19: - | X19: - | Y19: -303 | Z19: - | AA19: 434
B20: Statutory Reserve | C20: 484 | D20: - | E20: - | F20: - | G20: 77 | H20: - | I20: - | J20: 561 | K20: - | L20: - | M20: 128 | N20: - | O20: - | P20: - | Q20: - | R20: 689 | S20: 689 | T20: - | U20: - | V20: 115 | W20: - | X20: - | Y20: - | Z20: - | AA20: 804
B21: Special Economic Zone | C21: - | D21: - | E21: - | F21: - | G21: 5500 | H21: - | I21: - | J21: 5500 | K21: - | L21: - | M21: -525 | N21: - | O21: - | P21: - | Q21: - | R21: 4975 | S21: 4975 | T21: - | U21: - | V21: 4135 | W21: - | X21: - | Y21: - | Z21: - | AA21: 9110
B22: Reinvestment Reserve
B23: Securities Premium | C23: 41164 | D23: - | E23: - | F23: - | G23: - | H23: 24 | I23: 20207 | J23: 61395 | K23: - | L23: - | M23: - | N23: - | O23: 13104 | P23: 9 | Q23: - | R23: 74508 | S23: 74508 | T23: - | U23: - | V23: - | W23: - | X23: 39447 | Y23: 841 | Z23: - | AA23: 114796
B24: General Reserve | C24: 255016 | D24: - | E24: - | F24: - | G24: - | H24: - | I24: - | J24: 255016 | K24: - | L24: - | M24: - | N24: 3410 | O24: - | P24: - | Q24: - | R24: 258426 | S24: 258426 | T24: - | U24: - | V24: - | W24: 1795 | X24: - | Y24: - | Z24: - | AA24: 260221
B25: Retained Earnings | C25: 12330 | D25: 39354 | E25: -3852 | F25: -732 | G25: -5632 | H25: - | I25: -8496 | J25: 32972 | K25: 49128 | L25: -3921 | M25: 438 | N25: - | O25: - | P25: - | Q25: 117442 | R25: 196059 | S25: 196059 | T25: 60705 | U25: -4297 | V25: -4774 | W25: - | X25: - | Y25: - | Z25: 258 | AA25: 247951
B26: Other Comprehensive Income | C26: 62466 | D26: 15311 | E26: - | F26: - | G26: - | H26: - | I26: -181 | J26: 77596 | K26: 33849 | L26: - | M26: - | N26: - | O26: - | P26: - | Q26: 728 | R26: 112173 | S26: 112173 | T26: 22185 | U26: - | V26: - | W26: - | X26: - | Y26: - | Z26: - | AA26: 134358
B29: Total | C29: =SUBTOTAL(109,C9:C28) -> 381184 | D29: =SUBTOTAL(109,D9:D28) -> 54665 | E29: =SUBTOTAL(109,E9:E28) -> -3852 | F29: =SUBTOTAL(109,F9:F28) -> -732 | G29: =SUBTOTAL(109,G9:G28) -> 0 | H29: =SUBTOTAL(109,H9:H28) -> 35 | I29: =SUBTOTAL(109,I9:I28) -> 11526 | J29: 442827 | K29: 82977 | L29: -3921 | M29: - | N29: - | O29: 52947 | P29: 728 | Q29: 118169 | R29: 693727 | S29: =SUM(S9:S26) -> 693727 | T29: =SUM(T9:T26) -> 82890 | U29: =SUM(U9:U26) -> -4297 | V29: =SUM(V9:V26) -> 0 | W29: =SUM(W9:W26) -> 0 | X29: =SUM(X9:X26) -> -396 | Y29: =SUM(Y9:Y26) -> 538 | Z29: =SUM(Z9:Z26) -> 258 | AA29: =SUM(AA9:AA26) -> 772720
B33: Column1 | C33: 2019-20 | D33: 2020-21 | E33: 2021-22 | F33: 2022-23e | G33: 2023-24 | H33: 2024-25 | I33: 2025-26 | J33: 2026-27
B34: opening balance | C34: 381184 | D34: =+C40 -> 442826 | E34: =+S29 -> 693727 | F34: =E40 -> 772720 | G34: =F40 -> 864012.95 | H34: =G40 -> 968668.19 | I34: =H40 -> 1084911.4 | J34: =I40 -> 1214341.2
B35: add income of year | C35: =+D29 -> 54665 | D35: =+K29 -> 82977 | E35: =+T29 -> 82890 | F35: =profitloss!G43 -> 98164.464 | G35: =profitloss!H43 -> 112532.52 | H35: =profitloss!I43 -> 124992.73 | I35: =profitloss!J43 -> 139171.81 | J35: =profitloss!K43 -> 157477.06
B36: less dividend | C36: =+E29 -> -3852 | D36: =+L29 -> -3921 | E36: =+U29 -> -4297 | F36: =-profitloss!G53*0.9 -> -6871.5125 | G36: =-profitloss!H53*0.9 -> -7877.2764 | H36: =-profitloss!I53*0.9 -> -8749.4911 | I36: =-profitloss!J53*0.9 -> -9742.0268 | J36: =-profitloss!K53*0.9 -> -11023.394
B37: right issue | D37: =+O29 -> 52947
B38: other retained earning | C38: =-732+35 -> -697 | D38: =+P29 -> 728 | E38: 400
B39: adjustments | C39: =+I29 -> 11526 | D39: =+Q29 -> 118169 | F39: =profitloss!G39 -> 0
B40: closing bal | C40: =SUM(C34:C39) -> 442826 | D40: =SUM(D34:D39) -> 693726 | E40: =SUM(E34:E39) -> 772720 | F40: =SUBTOTAL(109,F34:F39) -> 864012.95 | G40: =SUBTOTAL(109,G34:G39) -> 968668.19 | H40: =SUBTOTAL(109,H34:H39) -> 1084911.4 | I40: =SUBTOTAL(109,I34:I39) -> 1214341.2 | J40: =SUBTOTAL(109,J34:J39) -> 1360794.9
B45: NCI | C45: Column1 | D45: Column2 | E45: Column3 | F45: 2022-23e | G45: 2023-24 | H45: 2024-25 | I45: 2025-26 | J45: 2026-27
B46: opening balance | F46: =balancesheet!F34 -> 109499 | G46: =F52 -> 119642.66 | H46: =G52 -> 131271.02 | I46: =H52 -> 144186.94 | J46: =I52 -> 158568.02
B47: add income of year | F47: =profitloss!G44 -> 10907.163 | G47: =profitloss!H44 -> 12503.613 | H47: =profitloss!I44 -> 13888.081 | I47: =profitloss!J44 -> 15463.535 | J47: =profitloss!K44 -> 17497.451
B48: less dividend | F48: =-profitloss!G53*0.1 -> -763.50138 | G48: =-profitloss!H53*0.1 -> -875.25293 | H48: =-profitloss!I53*0.1 -> -972.16568 | I48: =-profitloss!J53*0.1 -> -1082.4474 | J48: =-profitloss!K53*0.1 -> -1224.8216
B49: right issue
B50: other retained earning
B51: adjustments
B52: closing bal | F52: =SUM(F46:F51) -> 119642.66 | G52: =SUM(G46:G51) -> 131271.02 | H52: =SUM(H46:H51) -> 144186.94 | I52: =SUM(I46:I51) -> 158568.02 | J52: =SUM(J46:J51) -> 174840.65

Sheet debt
A1: debt
A3: Total Non-Current Liabilities | B3: 289692 | C3: 291652 | D3: 244212 | E3: 302019
A4: non current
A5: =balancesheet!A42 -> Provisions | B5: =balancesheet!C42 -> 2856 | C5: =balancesheet!D42 -> 1790 | D5: =balancesheet!E42 -> 2625 | E5: =balancesheet!F42 -> 1853
A6: =balancesheet!A43 -> Deferred Tax Liabilities (Net) | B6: =balancesheet!C43 -> 49923 | C6: =balancesheet!D43 -> 54123 | D6: =balancesheet!E43 -> 37001 | E6: =balancesheet!F43 -> 49644
B7: =B3-B5-B6 -> 236913 | C7: =C3-C5-C6 -> 235739 | D7: =D3-D5-D6 -> 204586 | E7: =E3-E5-E6 -> 250522
A8: interest exp
A9: =profitloss!A16 -> Finance Costs | B9: =profitloss!C16 -> 16495 | C9: =profitloss!D16 -> 22027 | D9: =profitloss!E16 -> 21189 | E9: =profitloss!F16 -> 14584
B11: =B9/B7 -> 0.069624715 | C11: =C9/C7 -> 0.093438082 | D11: =D9/D7 -> 0.10357014 | E11: =E9/E7 -> 0.058214448
A12: assumed interest | B12: 0.08
A13: assumed debt | B13: 0.25
A15: capital employes
A16: equity | B16: =SUM(balancesheet!C32:C34) -> 395392 | C16: =SUM(balancesheet!D32:D34) -> 461347 | D16: =SUM(balancesheet!E32:E34) -> 799432 | E16: =SUM(balancesheet!F32:F34) -> 888984
A17: debt | B17: =B7 -> 236913 | C17: =C7 -> 235739 | D17: =D7 -> 204586 | E17: =E7 -> 250522
A19: debt/equity | B19: =B17/(B16+B17) -> 0.37468152 | C19: =C17/(C16+C17) -> 0.33817779 | D19: =D17/(D16+D17) -> 0.20376726 | E19: =E17/(E16+E17) -> 0.21985141
A23: assumed debt equity | E23: 0.35
H24: particulars | I24: 2021-22 | J24: 2022-23E | K24: 2022-23E2 | L24: 2022-23E3 | M24: 2022-23E4 | N24: 2022-23E5
A25: capital required | B25: 2022-23E | C25: 2022-23E2 | D25: 2022-23E3 | E25: 2022-23E4 | F25: 2022-23E5 | H25: investment | I25: =balancesheet!F12 -> 286146 | J25: =I25*(1+$J$26) -> 343375.2 | K25: =J25*(1+$J$26) -> 412050.24 | L25: =K25*(1+$J$26) -> 494460.29 | M25: =L25*(1+$J$26) -> 593352.35 | N25: =M25*(1+$J$26) -> 712022.81
A26: fixed ASSET | B26: =PPE!H86 -> 38317.483 | C26: =PPE!I86 -> 58953.053 | D26: =PPE!J86 -> 69734.302 | E26: =PPE!K86 -> 81255.015 | F26: =PPE!L86 -> 93965.595 | J26: 0.2
A27: INVESTMENTS | B27: =J25-I25 -> 57229.2 | C27: =K25-J25 -> 68675.04 | D27: =L25-K25 -> 82410.048 | E27: =M25-L25 -> 98892.058 | F27: =N25-M25 -> 118670.47
A28: OTHER | B28: 3564 | H28: increase in price of investment | J28: =profitloss!G34 -> 52997.5 | K28: =profitloss!H34 -> 51365.5 | L28: =profitloss!I34 -> 52181.5 | M28: =profitloss!J34 -> 51773.5 | N28: =profitloss!K34 -> 51977.5
A29: CAPITAL REQIRED | B29: =SUM(B26:B28) -> 99110.683 | C29: =SUM(C26:C28) -> 127628.09 | D29: =SUM(D26:D28) -> 152144.35 | E29: =SUM(E26:E28) -> 180147.07 | F29: =SUM(F26:F28) -> 212636.06 | H29: investment value | J29: =+J25+J28 -> 396372.7 | K29: =+K25+K28 -> 463415.74 | L29: =+L25+L28 -> 546641.79 | M29: =+M25+M28 -> 645125.85 | N29: =+N25+N28 -> 764000.31
A31: Debt additional | B31: =B29*$B$13 -> 24777.671 | C31: =C29*$B$13 -> 31907.023 | D31: =D29*$B$13 -> 38036.087 | E31: =E29*$B$13 -> 45036.768 | F31: =F29*$B$13 -> 53159.016
A32: equity financed | B32: =0.75*B29 -> 74333.012 | C32: =0.75*C29 -> 95721.07 | D32: =0.75*D29 -> 114108.26 | E32: =0.75*E29 -> 135110.3 | F32: =0.75*F29 -> 159477.05
A34: opening | B34: =debt!E7 -> 250522 | C34: =B38 -> 275299.67 | D34: =C38 -> 307206.69 | E34: =D38 -> 345242.78 | F34: =E38 -> 390279.55
A35: add debt | B35: =B31 -> 24777.671 | C35: =C31 -> 31907.023 | D35: =D31 -> 38036.087 | E35: =E31 -> 45036.768 | F35: =F31 -> 53159.016
A38: closing | B38: =SUM(B34:B37) -> 275299.67 | C38: =SUM(C34:C37) -> 307206.69 | D38: =SUM(D34:D37) -> 345242.78 | E38: =SUM(E34:E37) -> 390279.55 | F38: =SUM(F34:F37) -> 443438.57
A40: interest | B40: =((B38+B34)/2)*8% -> 21032.867 | C40: =((C38+C34)/2)*8% -> 23300.255 | D40: =((D38+D34)/2)*8% -> 26097.979 | E40: =((E38+E34)/2)*8% -> 29420.893 | F40: =((F38+F34)/2)*8% -> 33348.725
A41: =balancesheet!A44 -> Other Non-Current Liabilities | B41: 610 | C41: 610 | D41: 610 | E41: 610 | F41: 610
A42: =balancesheet!A40 -> Deferred Payment Liabilities | B42: 13000 | C42: 13000 | D42: 13000 | E42: 13000 | F42: 13000
A43: =balancesheet!A41 -> oyher financial liablities | B43: 12031 | C43: 12031 | D43: 12031 | E43: 12031 | F43: 12031
A44: =balancesheet!A40 -> Deferred Payment Liabilities | B44: =balancesheet!$F$40 -> 37184 | C44: =balancesheet!$F$40 -> 37184 | D44: =balancesheet!$F$40 -> 37184 | E44: =balancesheet!$F$40 -> 37184 | F44: =balancesheet!$F$40 -> 37184
A45: =+balancesheet!A48 -> Borrowings | B45: =+B38-B44-B43-B42-B41 -> 212474.67 | C45: =+C38-C44-C43-C42-C41 -> 244381.69 | D45: =+D38-D44-D43-D42-D41 -> 282417.78 | E45: =+E38-E44-E43-E42-E41 -> 327454.55 | F45: =+F38-F44-F43-F42-F41 -> 380613.57

Sheet WORKING CAPITAL
A1: working capital | B1: Column1 | C1: 2018-19 | D1: 2019-20 | E1: 2020-21 | F1: 2021-22 | G1: 2022-23E | H1: 2023-24E | I1: 2024-25E | J1: 2025-26E | K1: 2026-27E
A3: =+profitloss!A11 -> Cost of Material Consumed | B3: =+profitloss!B11 | C3: =+profitloss!C11 -> 275237 | D3: =+profitloss!D11 -> 260621 | E3: =+profitloss!E11 -> 199915 | F3: =+profitloss!F11 -> 360784 | G3: =+profitloss!G11 -> 375272.88 | H3: =+profitloss!H11 -> 429915.48 | ... K3: =+profitloss!K11 -> 658791.27
A4: =+profitloss!A12 -> Purchase of Stock-in-Trade | B4: =+profitloss!B12 | C4: =+profitloss!C12 -> 123930 | D4: =+profitloss!D12 -> 149667 | E4: =+profitloss!E12 -> 101850 | F4: =+profitloss!F12 -> 135585 | G4: =+profitloss!G12 -> 183466.74 | H4: =+profitloss!H12 -> 210180.9 | ... K4: =+profitloss!K12 -> 322075.73
A5: =+profitloss!A13 -> Changes in Inventories of Finished Goods, Work-in-Progress and Stock-in-Trade | B5: =+profitloss!B13 -> 25 | C5: =+profitloss!C13 -> -4680 | D5: =+profitloss!D13 -> -5048 | E5: =+profitloss!E13 -> -9064 | F5: =+profitloss!F13 -> -21457
A6: COGS | C6: =SUM(C3:C5) -> 394487 | D6: =SUM(D3:D5) -> 405240 | E6: =SUM(E3:E5) -> 292701 | F6: =SUM(F3:F5) -> 474912 | G6: =SUM(G3:G5) -> 558739.62 | H6: =SUM(H3:H5) -> 640096.39 | I6: =SUM(I3:I5) -> 735584.78 | J6: =SUM(J3:J5) -> 848028.68 | K6: =SUM(K3:K5) -> 980867
A8: INVENTORY | C8: =balancesheet!C19 -> 67561 | D8: =balancesheet!D19 -> 73903 | E8: =balancesheet!E19 -> 81672 | F8: =balancesheet!F19 -> 107778 | G8: =G6*$C$11/365 -> 120073.6 | H8: =H6*$C$11/365 -> 137557.24 | I8: =I6*$C$11/365 -> 158077.77 | J8: =J6*$C$11/365 -> 182242.06 | K8: =K6*$C$11/365 -> 210789.12
A10: INVENTORY DAYS | C10: =C8/(C6/365) -> 62.51097 | D10: =D8/(D6/365) -> 66.564493 | E10: =E8/(E6/365) -> 101.8455 | F10: =F8/(F6/365) -> 82.83423
A11: AVERAGE | C11: =AVERAGE(C10:F10) -> 78.438798
A13: TRADE PAYABLE | C13: =balancesheet!C50 -> 108309 | D13: =balancesheet!D50 -> 96799 | E13: =balancesheet!E50 -> 108897 | F13: =balancesheet!F50 -> 159330 | G13: =G6*$C$16/365 -> 170549.74 | H13: =H6*$C$16/365 -> 195383.09 | I13: =I6*$C$16/365 -> 224529.97 | J13: =J6*$C$16/365 -> 258852.36 | K13: =K6*$C$16/365 -> 299399.94
A15: PAYABLE DAYS | C15: =C13/(C6/365) -> 100.21315 | D15: =D13/(D6/365) -> 87.186939 | E15: =E13/(E6/365) -> 135.79525 | F15: =F13/(F6/365) -> 122.45521
A16: AVERAGE | C16: =AVERAGE(C15:F15) -> 111.41264
A18: =profitloss!A7 -> REVENUE FROM OPERATIONS | C18: =profitloss!C7 -> 583094 | D18: =profitloss!D7 -> 612437 | E18: =profitloss!E7 -> 486326 | F18: =profitloss!F7 -> 721634 | G18: =profitloss!G7 -> 833939.73 | H18: =profitloss!H7 -> 955367.74 | I18: =profitloss!I7 -> 1097887.7 | J18: =profitloss!J7 -> 1265714.5 | K18: =profitloss!K7 -> 1463980.6
A20: TRADE RECIEVABLES | C20: =balancesheet!C22 -> 30089 | D20: =balancesheet!D22 -> 19656 | E20: =balancesheet!E22 -> 19014 | F20: =balancesheet!F22 -> 23640 | G20: =G18*$C$23/365 -> 34271.496 | H20: =H18*$C$23/365 -> 39261.688 | I20: =I18*$C$23/365 -> 45118.674 | J20: =J18*$C$23/365 -> 52015.662 | K20: =K18*$C$23/365 -> 60163.586
A21: RECIEVABLE DAYS | C21: =C20/(C18/365) -> 18.834845 | D21: =D20/(D18/365) -> 11.714576 | E21: =E20/(E18/365) -> 14.270489 | F21: =F20/(F18/365) -> 11.957031
C23: 15

Sheet PPE
C1: SHEET SUMMARY
C3: 1 | D3: NOTES TO ACCOUNTS
C4: 2 | D4: SUMMARY OF YEAR
C5: 3 | D5: TREND
C6: 4 | D6: ESTIMATION
A7: 1. PROPERTY, PLANT AND EQUIPMENT, OTHER INTANGIBLE ASSETS, CAPITAL WORK-IN-PROGRESS AND INTANGIBLE ASSETS UNDER DEVELOPMENT
B8: Description | C8: Gross Block | G8: Depreciation/Amortisation and Depletion | L8: Net Block | Q8: Gross Block | U8: Depreciation/Amortisation and Depletion | Y8: Net Block | AB8: Description | AC8: Gross Block Depreciation / Amortisation and Depletion Net Block
C9: As at 01-04-2019 | D9: Additions/ Adjustments^ | E9: Deductions/ Adjustments | F9: As at 31-03-2020 | G9: As at 01-04-2019 | H9: For the Year # | J9: Deductions/ Adjustments | K9: As at 31-03-2020 | L9: As at 31-03-2020 | M9: As at 31-03-2019 | P9: Description | Q9: As at Additions/ | R9: As at Additions/ | S9: Deductions/ | T9: As at | U9: As at | V9: For the | W9: Deductions/ | X9: As at | Y9: As at | Z9: As at | AC9: As at 01-04-2021 | AD9: Additions / Adjustments ^ | AE9: Deductions / Adjustments | AG9: As at 31-03-2022 | AH9: As at 01-04-2021 | AJ9: For the Year # | AL9: Deductions / Adjustments | AM9: As at 31-03-2022 | AN9: As at 31-03-2022 | AO9: As at 31-03-2021 | AP9: TOTAL %
B10: PROPERTY, PLANT AND EQUIPMENT | Q10: 01-04-2020 Adjustments^ | S10: Adjustments | T10: 44286 | U10: 43922 | V10: Year # | W10: Adjustments@ | X10: 44286 | Y10: 44286 | Z10: 43921 | AB10: Property, Plant and Equipment
B11: Own Assets: | P11: Property, Plant And Equipment Own Assets: | AB11: Own Assets:
B12: Land | C12: 49371 | D12: 482 | E12: 3 | F12: 49850 | G12: - | H12: - | J12: - | K12: - | L12: 49850 | M12: 49371 | P12: Land | Q12: 49850 | R12: 95 | S12: 7 | T12: 49938 | U12: - | V12: - | W12: - | X12: - | Y12: 49938 | Z12: 49850 | AB12: Land | AC12: 49938 | AD12: 288 | AE12: 45 | AG12: 50181 | AH12: - | AJ12: - | AL12: - | AM12: - | AN12: 50181 | AO12: 49938
B13: Buildings | C13: 27672 | D13: 4551 | E13: 51 | F13: 32172 | G13: 7978 | H13: 1380 | J13: 23 | K13: 9335 | L13: 22837 | M13: 19694 | P13: Buildings | Q13: 32172 | R13: 1684 | S13: 17 | T13: 33839 | U13: 9335 | V13: 1418 | W13: 9 | X13: 10744 | Y13: 23095 | Z13: 22837 | AB13: Buildings | AC13: 34067 | AD13: 7682 | AE13: 67 | AG13: 41682 | AH13: 10878 | AJ13: 4278 | AL13: 17 | AM13: 15139 | AN13: 26543 | AO13: 23189
B14: Plant and Machinery | C14: 318853 | D14: 126104 | E14: 3447 | F14: 441510 | G14: 115008 | H14: 11108 | J14: 2141 | K14: 123975 | L14: 317535 | M14: 203845 | P14: Plant & Machinery | Q14: 442006 | R14: 23164 | S14: 2545 | T14: 463075 | U14: 123740 | V14: 12845 | W14: 2093 | X14: 134492 | Y14: 328583 | Z14: 318266 | AB14: Plant & Machinery | AC14: 463097 | AD14: 43015 | AE14: 1240 | AG14: 504872 | AH14: 134726 | AJ14: 19360 | AL14: 892 | AM14: 153194 | AN14: 351678 | AO14: 328371
B15: Electrical Installations | C15: 10175 | D15: 5291 | E15: 308 | F15: 15158 | G15: 4716 | H15: 864 | J15: 297 | K15: 5283 | L15: 9875 | M15: 5459 | P15: Electrical Installations | Q15: 14708 | R15: 997 | S15: 371 | T15: 15334 | U15: 5283 | V15: 1137 | W15: 362 | X15: 6058 | Y15: 9276 | Z15: 9425 | AB15: Electrical Installations | AC15: 15334 | AD15: 3265 | AE15: 88 | AG15: 18511 | AH15: 6058 | AJ15: 1257 | AL15: 18 | AM15: 7297 | AN15: 11214 | AO15: 9276
B16: Equipments$ | C16: 9019 | D16: 4503 | E16: 333 | F16: 13189 | G16: 3947 | H16: 1143 | J16: 314 | K16: 4776 | L16: 8413 | M16: 5072 | P16: Equipments $ | Q16: 13143 | R16: 5402 | S16: - | T16: 18545 | U16: 5011 | V16: 1306 | W16: - | X16: 6317 | Y16: 12228 | Z16: 8132 | AB16: Equipments $ | AC16: 18523 | AD16: 14252 | AE16: 137 | AG16: 32638 | AH16: 6083 | AJ16: 1993 | AL16: 7 | AM16: 8069 | AN16: 24569 | AO16: 12440
B17: Furniture and Fixtures | C17: 2623 | D17: 899 | E17: 162 | F17: 3360 | G17: 1136 | H17: 346 | J17: 131 | K17: 1351 | L17: 2009 | M17: 1487 | P17: Furniture & Fixtures | Q17: 3360 | R17: 859 | S17: 37 | T17: 4182 | U17: 1351 | V17: 312 | W17: 17 | X17: 1646 | Y17: 2536 | Z17: 2009 | AB17: Furniture & Fixtures | AC17: 4182 | AD17: 2325 | AE17: 48 | AG17: 6459 | AH17: 1646 | AJ17: 454 | AL17: 20 | AM17: 2080 | AN17: 4379 | AO17: 2536
B18: Vehicles | C18: 697 | D18: 77 | E18: 55 | F18: 719 | G18: 524 | H18: 69 | J18: 52 | K18: 541 | L18: 178 | M18: 173 | P18: Vehicles | Q18: 719 | R18: 106 | S18: 31 | T18: 794 | U18: 541 | V18: 66 | W18: 29 | X18: 578 | Y18: 216 | Z18: 178 | AB18: Vehicles | AC18: 794 | AD18: 129 | AE18: 20 | AG18: 903 | AH18: 578 | AJ18: 95 | AL18: 20 | AM18: 653 | AN18: 250 | AO18: 216
B19: Ships | C19: 417 | D19: 90 | E19: 5 | F19: 502 | G19: 322 | H19: 12 | J19: 5 | K19: 329 | L19: 173 | M19: 95 | P19: Ships | Q19: 502 | R19: 3 | S19: - | T19: 505 | U19: 329 | V19: 16 | W19: - | X19: 345 | Y19: 160 | Z19: 173 | AB19: Ships | AC19: 505 | AD19: 3 | AE19: - | AG19: 508 | AH19: 345 | AJ19: 16 | AL19: - | AM19: 361 | AN19: 147 | AO19: 160
B20: Aircrafts and Helicopters | C20: 543 | D20: 90 | E20: - | F20: 633 | G20: 348 | H20: 78 | J20: - | K20: 426 | L20: 207 | M20: 195 | P20: Aircrafts and Helicopters | Q20: 633 | R20: 848 | S20: - | T20: 1481 | U20: 426 | V20: 49 | W20: - | X20: 475 | Y20: 1006 | Z20: 207 | AB20: Aircrafts and Helicopters | AC20: 1481 | AD20: 85 | AE20: - | AG20: 1566 | AH20: 475 | AJ20: 275 | AL20: - | AM20: 750 | AN20: 816 | AO20: 1006
B21: Sub-Total | C21: 419370 | D21: 142087 | E21: 4364 | F21: 557093 | G21: 133979 | H21: 15000 | J21: 2963 | K21: 146016 | L21: 411077 | M21: 285391 | P21: Sub-Total | Q21: 557093 | R21: 33608 | S21: 3008 | T21: 587693 | U21: 146016 | V21: 17149 | W21: 2510 | X21: 160655 | Y21: 427038 | Z21: 411077 | AB21: Sub-Total | AC21: 587921 | AD21: 71044 | AE21: 1645 | AG21: 657320 | AH21: 160789 | AJ21: 27728 | AL21: 974 | AM21: 187543 | AN21: 469777 | AO21: 427132 | AP21: =AO21/$AO$37 -> 0.80432204
B22: Right-of-Use Assets: | P22: Right-of-Use Assets: | AB22: Right-of-Use Assets:
B23: Land | C23: 18683 | D23: 210 | E23: - | F23: 18893 | G23: 1970 | H23: 310 | J23: - | K23: 2280 | L23: 16613 | M23: 16713 | P23: Land | Q23: 18893 | R23: 165 | S23: - | T23: 19058 | U23: 2280 | V23: 308 | W23: - | X23: 2588 | Y23: 16470 | Z23: 16613 | AB23: Land | AC23: 18830 | AD23: 849 | AE23: 5 | AG23: 19674 | AH23: 2454 | AJ23: 348 | AL23: - @ | AM23: 2802 | AN23: 16872 | AO23: 16376
B24: Buildings | C24: - | D24: 2225 | E24: 17 | F24: 2208 | G24: - | H24: 300 | J24: 1 | K24: 299 | L24: 1909 | M24: - | P24: Buildings | Q24: 2208 | R24: 652 | S24: 146 | T24: 2714 | U24: 299 | V24: 392 | W24: 55 | X24: 636 | Y24: 2078 | Z24: 1909 | AB24: Buildings | AC24: 2714 | AD24: 3269 | AE24: 104 | AG24: 5879 | AH24: 636 | AJ24: 883 | AL24: 59 | AM24: 1460 | AN24: 4419 | AO24: 2078
B25: Plant and Machinery | C25: 318 | D25: 7446 | E25: - | F25: 7764 | G25: 307 | H25: 1189 | J25: 8 | K25: 1488 | L25: 6276 | M25: 11 | P25: Plant & Machinery | Q25: 7764 | R25: 424 | S25: 84 | T25: 8104 | U25: 1488 | V25: 1248 | W25: 81 | X25: 2655 | Y25: 5449 | Z25: 6276 | AB25: Plant & Machinery | AC25: 8104 | AD25: 5889 | AE25: - | AG25: 13993 | AH25: 2655 | AJ25: 1968 | AL25: - | AM25: 4623 | AN25: 9370 | AO25: 5449
B26: Vehicles | C26: - | D26: 57 | E26: -2 | F26: 59 | G26: - | H26: 14 | J26: - | K26: 14 | L26: 45 | M26: - | P26: Vehicles | Q26: 59 | R26: 2 | S26: - | T26: 61 | U26: 14 | V26: 16 | W26: - | X26: 30 | Y26: 31 | Z26: 45 | AB26: Vehicles | AC26: 61 | AD26: - | AE26: - | AG26: 61 | AH26: 30 | AJ26: 15 | AL26: - | AM26: 45 | AN26: 16 | AO26: 31
B27: Ships | C27: 10 | D27: - | E27: - | F27: 10 | G27: 10 | H27: - | J27: - | K27: 10 | L27: - | M27: - | P27: Ships | Q27: 10 | R27: 0 | S27: - | T27: 10 | U27: 10 | V27: - | W27: - | X27: 10 | Y27: - | Z27: - | AB27: Ships | AC27: 10 | AD27: - | AE27: - | AG27: 10 | AH27: 10 | AJ27: - | AL27: - | AM27: 10 | AN27: - | AO27: -
B28: Sub-Total | C28: 19011 | D28: 9938 | E28: 15 | F28: 28934 | G28: 2287 | H28: 1813 | J28: 9 | K28: 4091 | L28: 24843 | M28: 16724 | P28: Sub-Total | Q28: 28934 | R28: 1243 | S28: 230 | T28: 29947 | U28: 4091 | V28: 1964 | W28: 136 | X28: 5919 | Y28: 24028 | Z28: 24843 | AB28: Sub-Total | AC28: 29719 | AD28: 10007 | AE28: 109 | AG28: 39617 | AH28: 5785 | AJ28: 3214 | AL28: 59 | AM28: 8940 | AN28: 30677 | AO28: 23934 | AP28: =AO28/$AO$37 -> 0.045069542
B29: Total (A) | C29: 438381 | D29: 152025 | E29: 4379 | F29: 586027 | G29: 136266 | H29: 16813 | J29: 2972 | K29: 150107 | L29: 435920 | M29: 302115 | P29: Total (A) | Q29: 586027 | R29: 34851 | S29: 3238 | T29: 617640 | U29: 150107 | V29: 19113 | W29: 2646 | X29: 166574 | Y29: 451066 | Z29: 435920 | AB29: Total (A) | AC29: 617640 | AD29: 81051 | AE29: 1754 | AG29: 696937 | AH29: 166574 | AJ29: 30942 | AL29: 1033 | AM29: 196483 | AN29: 500454 | AO29: 451066 | AP29: =AO29/$AO$37 -> 0.84939158
B30: OTHER INTANGIBLE ASSETS * | P30: Other Intangible Assets * | AB30: Other Intangible Assets *
B31: Technical Knowhow Fees | C31: 5406 | D31: 535 | E31: -20 | F31: 5961 | G31: 3756 | H31: 245 | J31: -20 | K31: 4021 | L31: 1940 | M31: 1650 | P31: Technical Knowhow Fees | Q31: 5961 | R31: 55 | S31: 27 | T31: 5989 | U31: 4021 | V31: 173 | W31: 27 | X31: 4167 | Y31: 1822 | Z31: 1940 | AB31: Technical Knowhow Fees | AC31: 5989 | AD31: 90 | AE31: - | AG31: 6079 | AH31: 4167 | AJ31: 173 | AL31: - | AM31: 4340 | AN31: 1739 | AO31: 1822
B32: Spectrum Cost | C32: 58139 | D32: 2768 | E32: - | F32: 60907 | G32: 2919 | H32: 2485 | J32: - | K32: 5404 | L32: 55503 | M32: 55220 | P32: Spectrum Cost | Q32: 60907 | R32: 0 | S32: - | T32: 60907 | U32: 5404 | V32: 4214 | W32: - | X32: 9618 | Y32: 51289 | Z32: 55503 | AB32: Spectrum Cost | AC32: 60907 | AD32: 32270 | AE32: - | AG32: 93177 | AH32: 9618 | AJ32: 3855 | AL32: - | AM32: 13473 | AN32: 79704 | AO32: 51289
B33: Software | C33: 8294 | D33: 1460 | E33: 273 | F33: 9481 | G33: 2613 | H33: 1045 | J33: 232 | K33: 3426 | L33: 6055 | M33: 5681 | P33: Software | Q33: 9481 | R33: 3889 | S33: 8 | T33: 13362 | U33: 3426 | V33: 1368 | W33: 4 | X33: 4790 | Y33: 8572 | Z33: 6055 | AB33: Software | AC33: 12328 | AD33: 1622 | AE33: - | AG33: 13950 | AH33: 4790 | AJ33: 1544 | AL33: - | AM33: 6334 | AN33: 7616 | AO33: 7538
B34: Development Rights | C34: 69362 | D34: 2081 | E34: 6201 | F34: 65242 | G34: 51165 | H34: 1740 | J34: 6472 | K34: 46433 | L34: 18809 | M34: 18197 | P34: Development Rights | Q34: 65242 | R34: 7559 | S34: 11649 | T34: 61152 | U34: 46433 | V34: 1664 | W34: 684 | X34: 47413 | Y34: 13739 | Z34: 18809 | AB34: Development Rights | AC34: 61152 | AD34: 3868 | AE34: 18138 | AG34: 46882 | AH34: 47413 | AJ34: 2506 | AL34: 17433 | AM34: 32486 | AN34: 14396 | AO34: 13739
B35: Others | C35: 4943 | D35: 992 | E35: 24 | F35: 5911 | G35: 1429 | H35: 341 | J35: 31 | K35: 1739 | L35: 4172 | M35: 3514 | P35: Others | Q35: 5911 | R35: 647 | S35: 8 | T35: 6550 | U35: 1739 | V35: 261 | W35: 8 | X35: 1992 | Y35: 4558 | Z35: 4172 | AB35: Others | AC35: 7584 | AD35: 6023 | AE35: 17 | AG35: 13590 | AH35: 1992 | AJ35: 733 | AL35: 15 | AM35: 2710 | AN35: 10880 | AO35: 5592
B36: Total (B) | C36: 146144 | D36: 7836 | E36: 6478 | F36: 147502 | G36: 61882 | H36: 5856 | J36: 6715 | K36: 61023 | L36: 86479 | M36: 84262 | P36: Total (B) | Q36: 147502 | R36: 12150 | S36: 11692 | T36: 147960 | U36: 61023 | V36: 7680 | W36: 723 | X36: 67980 | Y36: 79980 | Z36: 86479 | AB36: Total (B) | AC36: 147960 | AD36: 43873 | AE36: 18155 | AG36: 173678 | AH36: 67980 | AJ36: 8811 | AL36: 17448 | AM36: 59343 | AN36: 114335 | AO36: 79980 | AP36: =AO36/$AO$37 -> 0.15060842
B37: Total (A+B) | C37: 584525 | D37: 159861 | E37: 10857 | F37: 733529 | G37: 198148 | H37: 22669 | J37: 9687 | K37: 211130 | L37: 522399 | M37: 386377 | P37: Total (A+B) | Q37: 733529 | R37: 47001 | S37: 14930 | T37: 765600 | U37: 2,11,130 | V37: 26793 | W37: 3369 | X37: 234554 | Y37: 531046 | Z37: 522399 | AB37: Total (A+B) | AC37: 765600 | AD37: 124924 | AE37: 19909 | AG37: 870615 | AH37: 234554 | AJ37: 39753 | AL37: 18481 | AM37: 255826 | AN37: 614789 | AO37: 531046 | AP37: 100
K38: =+K37-G37 -> 12982 | AB38: Previous Year | AC38: 733529 | AD38: 47001 | AE38: 14930 | AG38: 765600 | AH38: 211130 | AJ38: 26793 | AL38: 3369 | AM38: 234554 | AN38: 531046 | AO38: 522399
B39: Previous Year | C39: 5,75,471 | D39: 74395 | E39: 65341 | F39: 5,84,525 | G39: 1,77,399 | H39: 24290 | J39: 3541 | K39: 1,98,148 | L39: 3,86,377 | P39: Previous Year | Q39: 584525 | R39: 159861 | S39: 10857 | T39: 733529 | U39: 1,98,148 | V39: 22669 | W39: 9687 | X39: 211130 | Y39: 522399 | Z39: 386377 | AB39: Capital Work-in-Progress | AN39: 68052 | AO39: 71171
B40: CAPITAL WORK-IN- PROGRESS | L40: 59096 | M40: 1,50,178 | P40: Capital Work-Inprogress | X40: 71171 | Z40: 59096 | AB40: Intangible Assets Under Development | AN40: 104454 | AO40: 54782
B41: INTANGIBLE ASSETS UNDER DEVELOPMENT | L41: 50010 | M41: 29285 | P41: Intangible Assets Under Development | X41: 54782 | Z41: 50010
C42: gross | G42: DEPRICIATION | K42: net block
B43: summary | C43: opening bal | D43: additions | E43: deductions | F43: closing bal | G43: opening bal2 | H43: additions3 | I43: deductions4 | J43: closing bal5 | K43: opening | L43: closing | P43: PARTICULARS | Q43: OPENING BAL | R43: ADDITION | S43: DELETION | T43: CLOSINGBAL | U43: OPENING DEP | V43: ADD DEP | W43: REDUCTIONS | X43: CLOSING DEO | Y43: CLOSING BAL | Z43: OPENING BAL2 | AB43: PARTICULARS | AC43: OPENING BAL | AD43: ADDITION | AE43: DELETION | AF43: CLOSINGBAL | AG43: OPENING DEP | AH43: ADD DEP | AI43: REDUCTIONS | AJ43: CLOSING DEO | AK43: CLOSING BAL | AL43: OPENING BAL2
B44: Plant property and equipment | C44: =C21 -> 419370 | D44: =D21 -> 142087 | E44: =E21 -> 4364 | F44: =+C44+D44-E44 -> 557093 | G44: =G21 -> 133979 | H44: =H21 -> 15000 | I44: =J21 -> 2963 | J44: =G44+H44-I44 -> 146016 | K44: =M21 -> 285391 | L44: =L21 -> 411077 | P44: PPE | Q44: =Q29 -> 586027 | R44: =R29 -> 34851 | S44: =S29 -> 3238 | T44: =T29 -> 617640 | U44: =U29 -> 150107 | V44: =V29 -> 19113 | W44: =W29 -> 2646 | X44: =X29 -> 166574 | ... Z44: =Z29 -> 435920 | AB44: PPE | AC44: =AC21 -> 587921 | AD44: =AD21 -> 71044 | AE44: =AE21 -> 1645 | AF44: =AG21 -> 657320 | AG44: =AH21 -> 160789 | AH44: =AJ21 -> 27728 | AI44: =AL21 -> 974 | AJ44: =AM21 -> 187543 | AK44: =AN21 -> 469777 | AL44: =AO21 -> 427132
B45: workings | K45: =+C44-G44 -> 285391 | L45: =+F44-J44 -> 411077 | Y45: =+T44-X44 -> 451066 | AK45: =+AF44-AJ44 -> 469777
B46: depreciation rate | K46: =G44/C44 -> 0.31947683 | L46: =J44/F44 -> 0.26210345 | Y46: =X44/T44 -> 0.26969432 | Z46: =U44/Q44 -> 0.25614349 | AK46: =AJ44/AF44 -> 0.28531461 | AL46: =AG44/AC44 -> 0.27348742
B47: right to use asset | C47: =+C28 -> 19011 | D47: =+D28 -> 9938 | E47: =+E28 -> 15 | F47: =+F28 -> 28934 | G47: =+G28 -> 2287 | H47: =+H28 -> 1813 | I47: 9 | J47: =+G47+H47-I47 -> 4091 | K47: =+M28 -> 16724 | L47: =+L28 -> 24843 | P47: RIGHT TO USE ASSET | Q47: =Q28 -> 28934 | R47: =R28 -> 1243 | S47: =S28 -> 230 | T47: =T28 -> 29947 | U47: =U28 -> 4091 | V47: =V28 -> 1964 | W47: =W28 -> 136 | X47: =X28 -> 5919 | ... Z47: =Z28 -> 24843 | AB47: RIGHT TO USE ASSET | AC47: =AC28 -> 29719 | AD47: =AD28 -> 10007 | AE47: =AE28 -> 109 | AF47: =AG28 -> 39617 | AG47: =AH28 -> 5785 | AH47: =AJ28 -> 3214 | AI47: =AL28 -> 59 | AJ47: =AM28 -> 8940 | AK47: =AN28 -> 30677 | AL47: =AO28 -> 23934
K49: =G47/C47 -> 0.12029877 | L49: =J47/F47 -> 0.14139075 | Y49: =X47/T47 -> 0.19764918 | Z49: =U47/Q47 -> 0.14139075 | AK49: =AJ47/AF47 -> 0.2256607 | AL49: =AG47/AC47 -> 0.19465662
P50: IBTANGIBLE ASSSET | Q50: =Q36 -> 147502 | R50: =R36 -> 12150 | S50: =S36 -> 11692 | T50: =T36 -> 147960 | U50: =U36 -> 61023 | V50: =V36 -> 7680 | W50: =W36 -> 723 | X50: =X36 -> 67980 | ... Z50: =Z36 -> 86479 | AB50: IBTANGIBLE ASSSET | AC50: =AC36 -> 147960 | AD50: =AD36 -> 43873 | AE50: =AE36 -> 18155 | AF50: =AG36 -> 173678 | AG50: =AH36 -> 67980 | AH50: =AJ36 -> 8811 | AI50: =AL36 -> 17448 | AJ50: =AM36 -> 59343 | AK50: =AN36 -> 114335 | AL50: =AO36 -> 79980
B51: intangible asset | C51: =C36 -> 146144 | D51: =D36 -> 7836 | E51: =E36 -> 6478 | F51: =F36 -> 147502 | G51: =G36 -> 61882 | H51: =H36 -> 5856 | I51: =J36 -> 6715 | J51: =K36 -> 61023 | K51: =M36 -> 84262 | L51: =L36 -> 86479
Y52: =X50/T50 -> 0.4594485 | Z52: =U50/Q50 -> 0.41370964 | AK52: =AJ50/AF50 -> 0.34168404 | AL52: =AG50/AC50 -> 0.4594485
K53: =G51/C51 -> 0.42343168 | L53: =J51/F51 -> 0.41370964
B55: CURRENT SUMMARY | C55: FIXED ASSET % | D55: DEPRECIATRON RATE | Q55: =C37 -> 584525 | R55: =Q37 -> 733529 | S55: =AC37 -> 765600 | T55: =AN37 -> 614789
B56: PLANT PROPERTY & EQUIPMENT | C56: 0.8 | D56: 0.28 | O56: =profitloss!A17 -> Depreciation/Amortisation and Depletion Expense | Q56: =profitloss!C17 -> 20934 | R56: =profitloss!D17 -> 22203 | S56: =profitloss!E17 -> 26572 | T56: =profitloss!F17 -> 29797
B57: RIGHT TOUSE ASSET | C57: 0.05 | D57: 0.15 | AI57: =255-234 -> 21
B58: INTANGIBLE ASSET | C58: 0.15 | D58: 0.43 | O58: drpriciation % | Q58: =Q56/Q55 -> 0.035813695 | R58: =R56/R55 -> 0.030268742 | S58: =S56/S55 -> 0.034707419 | T58: =T56/T55 -> 0.048467035
B59: Assumption company would generate more sales on per rupee fixed assets
B60: Column1 | C60: 2019 | D60: 2020 | E60: 2021 | F60: 2022 | G60: Column2 | H60: 2022-23E | I60: 2023-24E | J60: 2024-25E | K60: 2025-26E | L60: 2026-27E
B61: PLANT property and equipment | C61: =C37 -> 584525 | D61: =F37 -> 733529 | E61: =T37 -> 765600 | F61: =AG37 -> 870615 | H61: =H63/H65 -> 877831.29 | I61: =I63/I65 -> 909874.04 | J61: =J63/J65 -> 954684.98 | K61: =K63/K65 -> 1012571.6 | L61: =L63/L65 -> 1084430.1
B62: (GROSS)
B63: TURNOVER | C63: =revenue!B17 -> 583094 | D63: =revenue!C17 -> 612437 | E63: =revenue!D17 -> 486236 | F63: =revenue!E17 -> 721634 | H63: =Table18[[#Totals],[2022-23E]] -> 833939.73 | I63: =Table18[[#Totals],[2023-24E]] -> 955367.74 | J63: =Table18[[#Totals],[2024-25E]] -> 1097887.7 | K63: =Table18[[#Totals],[2025-26E]] -> 1265714.5 | L63: =Table18[[#Totals],[2026-27E]] -> 1463980.6
B65: Fixed turnover ratio | C65: =C63/C61 -> 0.99755186 | D65: =D63/D61 -> 0.83491859 | E65: =E63/E61 -> 0.63510449 | F65: =F63/F61 -> 0.82887844 | H65: 0.95 | I65: 1.05 | J65: 1.15 | K65: 1.25 | L65: 1.35
B68: PLANT PROPERTY & EQUIPMENT | H68: =H61*$C$56 -> 702265.04 | I68: =I61*$C$56 -> 727899.23 | J68: =J61*$C$56 -> 763747.98 | K68: =K61*$C$56 -> 810057.25 | L68: =L61*$C$56 -> 867544.06
B69: RIGHT TOUSE ASSET | H69: =H61*$C$57 -> 43891.565 | I69: =I61*$C$57 -> 45493.702 | J69: =J61*$C$57 -> 47734.249 | K69: =K61*$C$57 -> 50628.578 | L69: =L61*$C$57 -> 54221.504
B70: INTANGIBLE ASSET | H70: =H61*$C$58 -> 131674.69 | I70: =I61*$C$58 -> 136481.11 | J70: =J61*$C$58 -> 143202.75 | K70: =K61*$C$58 -> 151885.73 | L70: =L61*$C$58 -> 162664.51
B72: depriciation | C72: Column1 | D72: Column2 | E72: Column3 | F72: Column4 | G72: Column5 | H72: 2022-23E | I72: 2023-24E | J72: 2024-25E | K72: 2025-26E | L72: 2026-27E
B73: PLANT PROPERTY & EQUIPMENT | H73: =H68*$D$56 -> 196634.21 | I73: =I68*$D$56 -> 203811.78 | J73: =J68*$D$56 -> 213849.44 | K73: =K68*$D$56 -> 226816.03 | L73: =L68*$D$56 -> 242912.34
B74: RIGHT TOUSE ASSET | H74: =H69*$D$57 -> 6583.7347 | I74: =I69*$D$57 -> 6824.0553 | J74: =J69*$D$57 -> 7160.1374 | K74: =K69*$D$57 -> 7594.2867 | L74: =L69*$D$57 -> 8133.2255
B75: INTANGIBLE ASSET | H75: =H70*$D$58 -> 56620.119 | I75: =I70*$D$58 -> 58686.876 | J75: =J70*$D$58 -> 61577.181 | K75: =K70*$D$58 -> 65310.866 | L75: =L70*$D$58 -> 69945.74
B76: Total | H76: =SUBTOTAL(109,Table22[2022-23E]) -> 259838.06 | I76: =SUBTOTAL(109,Table22[2023-24E]) -> 269322.72 | J76: =SUBTOTAL(109,Table22[2024-25E]) -> 282586.75 | K76: =SUBTOTAL(109,Table22[2025-26E]) -> 299721.18 | L76: =SUBTOTAL(109,Table22[2026-27E]) -> 320991.3
B78: net block | C78: Column1 | D78: Column2 | E78: Column3 | F78: Column4 | G78: Column5 | H78: 2022-23E | I78: 2022-23E6 | J78: 2022-23E7 | K78: 2022-23E8 | L78: 2022-23E9
B79: PLANT PROPERTY & EQUIPMENT | H79: =H68-H73 -> 505630.83 | I79: =+I68-I73 -> 524087.45 | J79: =+J68-J73 -> 549898.55 | K79: =+K68-K73 -> 583241.22 | L79: =+L68-L73 -> 624631.72
B80: RIGHT TOUSE ASSET | H80: =+H69-H74 -> 37307.83 | I80: =+I69-I74 -> 38669.647 | J80: =+J69-J74 -> 40574.112 | K80: =+K69-K74 -> 43034.291 | L80: =+L69-L74 -> 46088.278
B81: INTANGIBLE ASSET | H81: =+H70-H75 -> 75054.576 | I81: =+I70-I75 -> 77794.23 | J81: =+J70-J75 -> 81625.566 | K81: =+K70-K75 -> 86574.868 | L81: =+L70-L75 -> 92718.771
B82: total | G82: 614789 | H82: =SUM(H79:H81) -> 617993.23 | I82: =SUM(I79:I81) -> 640551.32 | J82: =SUM(J79:J81) -> 672098.23 | K82: =SUM(K79:K81) -> 712850.38 | L82: =SUM(L79:L81) -> 763438.77
B84: opening bal | H84: 614789 | I84: =H87 -> 617993.23 | J84: =I87 -> 640551.32 | K84: =J87 -> 672098.23 | L84: =K87 -> 712850.38
B85: depriciation | H85: =+H61*4% -> 35113.252 | I85: =+I61*4% -> 36394.962 | J85: =+J61*4% -> 38187.399 | K85: =+K61*4% -> 40502.862 | L85: =+L61*4% -> 43377.203
B86: aquire | H86: =H87-(H84-H85) -> 38317.483 | I86: =I87-(I84-I85) -> 58953.053 | J86: =J87-(J84-J85) -> 69734.302 | K86: =K87-(K84-K85) -> 81255.015 | L86: =L87-(L84-L85) -> 93965.595
B87: closing bal | H87: =+H82 -> 617993.23 | I87: =+I82 -> 640551.32 | J87: =+J82 -> 672098.23 | K87: =+K82 -> 712850.38 | L87: =+L82 -> 763438.77

Sheet revenue
D1: Revenue sheet index
D2: 1 | E2: notes to accounts
D3: 2 | E3: segment wise estimation
D4: 3 | E4: expected revenue
D5: 4 | E5: other income
A7: Column1 | B7: 2018-19 | C7: 2019-20 | D7: 2020-21 | E7: 2021-22 | G7: Column1 | H7: 2018-19 | I7: 2019-20 | J7: 2020-21 | K7: 2021-22 | L7: Column2 | M7: Column3
A8: 23 REVENUE FROM OPERATIONS | G8: 24 OTHER INCOME INTEREST
A9: DISAGGREGATED REVENUE
G10: Bank Deposits | H10: 180 | I10: 473 | J10: 213 | K10: 99
A11: Oil to Chemicals | B11: =306154+139259 -> 445413 | C11: 423222 | D11: 301587 | E11: 479083 | G11: Debt instruments | H11: 4432 | I11: 9133 | J11: 9408 | K11: 11463
A12: Oil and Gas | B12: 4384 | C12: 2666 | D12: 1596 | E12: 4952 | G12: Other Financial Assets measured at Amortised Cost | H12: 282 | I12: 385 | J12: 589 | K12: 790
A13: Organised Retail | B13: 115257 | C13: 141237 | D13: 133935 | E13: 170942 | G13: Others | H13: 58 | I13: 326 | J13: 156 | K13: 177
A14: Digital Services | B14: 3896 | C14: 11994 | D14: 13691 | E14: 12041 | H14: 4952 | I14: 10317 | J14: 10366 | K14: 12529
A15: Financial Services | B15: 250 | C15: 1550 | D15: 1077 | E15: 748
A16: Others | B16: 13894 | C16: 31768 | D16: 34440 | E16: 53868 | G16: DIVIDEND INCOME | H16: 501 | I16: 110 | J16: 39 | K16: 41
A17: Total* | B17: 583094 | C17: =SUBTOTAL(109,C8:C16) -> 612437 | D17: 486236 | E17: 721634
G18: OTHER NON-OPERATING INCOME | H18: 442 | I18: 1464 | J18: 958 | K18: 1025
G20: GAIN ON FINANCIAL ASSETS
G21: Realised Gain | H21: 1703 | I21: 2180 | J21: 5066 | K21: 1139 | Q21: =14947-10904 -> 4043
G22: Unrealised Gain / (Loss) | J22: 102 | K22: 213
H23: 2471 | I23: 2076 | J23: 4964 | K23: 1352 | M23: =+J25-segmentrevenue!J17 -> 6808
G24: PROFIT / (LOSS) ON DIVESTMENT | H24: 20 | I24: -11
G25: Total | H25: 8386 | I25: 13956 | J25: 16327 | K25: 14947
A27: OIL to Chemicals | H27: OIL & gas
B28: =Table1[[#Headers],[2018-19]] -> 2018-19 | C28: =Table1[[#Headers],[2019-20]] -> 2019-20 | D28: =Table1[[#Headers],[2020-21]] -> 2020-21 | E28: =Table1[[#Headers],[2021-22]] -> 2021-22 | I28: 2018-19 | J28: 2019-20 | K28: 2020-21 | L28: 2021-22
A29: Revenue | B29: =B11 -> 445413 | C29: =C11 -> 423222 | D29: =D11 -> 301587 | E29: =E11 -> 479083 | H29: Revenue | I29: =B12 -> 4384 | J29: =C12 -> 2666 | K29: =D12 -> 1596 | L29: =E12 -> 4952
A30: growth rate | C30: =C29/B29-1 -> -0.049821177 | D30: =D29/C29-1 -> -0.28740236 | E30: =E29/D29-1 -> 0.58853996 | H30: growth rate | J30: =J29/I29-1 -> -0.39187956 | K30: =K29/J29-1 -> -0.40135034 | L30: =L29/K29-1 -> 2.1027569
A32: top to down growth rate approch
C33: rate of growth | H33: same assumed as inoil except international | K33: 0.075
A34: GDP FROWTH RATE | B34: 0.075 | C34: 0.075
A35: Prices of Crude oil and gas has been significantly | C35: 0.02
A36: sanction on russia has increased petrol prices
A37: after covid 19 oil and gas demad has been increased to normal | C37: 0 | H37: particulars2 | I37: 2021-022 | J37: 2022-23E | K37: 2023-24E | L37: 2024-25E | M37: 2025-26E | N37: 2026-27E
A38: hence no rise has been attributed to normalcy of demand | H38: Revenue | I38: =L29 -> 4952 | J38: =I38*(1+J39) -> 5323.4 | K38: =J38*(1+K39) -> 5722.655 | L38: =K38*(1+L39) -> 6151.8541 | M38: =L38*(1+M39) -> 6613.2432 | N38: =M38*(1+N39) -> 7109.2364
A39: due to saudi arabia and usa conflict OPEC has restricted supply | C39: 0.025 | H39: Growth | J39: =$K$33 -> 0.075 | K39: =$K$33 -> 0.075 | L39: =$K$33 -> 0.075 | M39: =$K$33 -> 0.075 | N39: =$K$33 -> 0.075
A40: it acts as an inflation in oil sector
A41: annual increase in 2022-23 | C41: =SUM(C34:C40) -> 0.12
A42: increase thereafter as russia sanction not to be lifted & increase thereafter | C42: 0.1
A44: PARTICULARS | B44: 2021-22 | C44: 2022-23E | D44: 2023-24E | E44: 2024-25E | F44: 2025-26E | G44: 2026-27E
A45: SALES EXPECTED | B45: =E29 -> 479083 | C45: =B45*(1+C46) -> 536572.96 | D45: =C45*(1+D46) -> 590230.26 | E45: =D45*(1+E46) -> 649253.28 | F45: =E45*(1+F46) -> 714178.61 | G45: =F45*(1+G46) -> 785596.47
A46: GROWTH RATE | C46: =C41 -> 0.12 | D46: =$C$42 -> 0.1 | E46: =$C$42 -> 0.1 | F46: =$C$42 -> 0.1 | G46: =$C$42 -> 0.1
A48: ORGANISATION RETAIL | H48: others
B49: =Table1[[#Headers],[2018-19]] -> 2018-19 | C49: =Table1[[#Headers],[2019-20]] -> 2019-20 | D49: =Table1[[#Headers],[2020-21]] -> 2020-21 | E49: =Table1[[#Headers],[2021-22]] -> 2021-22 | I49: =Table1[[#Headers],[2018-19]] -> 2018-19 | J49: =Table1[[#Headers],[2019-20]] -> 2019-20 | K49: =Table1[[#Headers],[2020-21]] -> 2020-21 | L49: =Table1[[#Headers],[2021-22]] -> 2021-22
A50: Revenue | B50: =B13 -> 115257 | C50: =C13 -> 141237 | D50: =D13 -> 133935 | E50: =E13 -> 170942 | H50: Revenue | I50: =B16 -> 13894 | J50: =C16 -> 31768 | K50: =D16 -> 34440 | L50: =E16 -> 53868
A51: growth rate | C51: =C50/B50-1 -> 0.2254093 | D51: =D50/C50-1 -> -0.051700333 | E51: =E50/D50-1 -> 0.27630567 | H51: growth rate | J51: =J50/I50-1 -> 1.2864546 | K51: =K50/J50-1 -> 0.084109796 | L51: =L50/K50-1 -> 0.5641115
A53: presumed to be sales grow at current rate | C53: 0.23 | H53: growth rate assumed | I53: 0.22
A54: reliance has aquired many brands to be sold by it | C54: 0 | H54: particulars2 | I54: 2021-022 | J54: 2022-23E | K54: 2023-24E | L54: 2024-25E | M54: 2025-26E | N54: 2026-27E
A55: It includes international brand and campa cola | C55: 0.025 | H55: Revenue | I55: =L50 -> 53868 | J55: =I55*(1+J56) -> 65718.96 | K55: =J55*(1+K56) -> 80177.131 | L55: =K55*(1+L56) -> 97816.1 | M55: =L55*(1+M56) -> 119335.64 | N55: =M55*(1+N56) -> 145589.48
A56: sales increasing in covid 19 | C56: 0 | H56: Growth | J56: =$I$53 -> 0.22 | K56: =$I$53 -> 0.22 | L56: =$I$53 -> 0.22 | M56: =$I$53 -> 0.22 | N56: =$I$53 -> 0.22
A57: at very good rate more than 24% | C57: -0.015
A58: inflation impact reduces sales in retail sector | C58: =SUM(C53:C57) -> 0.24
A60: PARTICULARS | B60: 2021-22 | C60: 2022-23E | D60: 2023-24E | E60: 2024-25E | F60: 2025-26E | G60: 2026-27E
A61: SALES EXPECTED | B61: =E50 -> 170942 | C61: =B61*(1+C62) -> 211968.08 | D61: =C61*(1+D62) -> 262840.42 | E61: =D61*(1+E62) -> 325922.12 | F61: =E61*(1+F62) -> 404143.43 | G61: =F61*(1+G62) -> 501137.85
A62: GROWTH RATE | C62: =$C$58 -> 0.24 | D62: =$C$58 -> 0.24 | E62: =$C$58 -> 0.24 | F62: =$C$58 -> 0.24 | G62: =$C$58 -> 0.24
A64: Financial services | H64: Digital Services
B65: =Table1[[#Headers],[2018-19]] -> 2018-19 | C65: =Table1[[#Headers],[2019-20]] -> 2019-20 | D65: =Table1[[#Headers],[2020-21]] -> 2020-21 | E65: =Table1[[#Headers],[2021-22]] -> 2021-22
A66: financial services | B66: =B15 -> 250 | C66: =C15 -> 1550 | D66: =D15 -> 1077 | E66: =E15 -> 748 | I66: =Table1[[#Headers],[2018-19]] -> 2018-19 | J66: =Table1[[#Headers],[2019-20]] -> 2019-20 | K66: =Table1[[#Headers],[2020-21]] -> 2020-21 | L66: =Table1[[#Headers],[2021-22]] -> 2021-22
C67: =C66/B66-1 -> 5.2 | D67: =D66/C66-1 -> -0.30516129 | E67: =E66/D66-1 -> -0.30547818 | H67: Revenue | I67: =B14 -> 3896 | J67: =C14 -> 11994 | K67: =D14 -> 13691 | L67: =E14 -> 12041
A68: financial services has seen a drastic fall | H68: growth rate | J68: =J67/I67-1 -> 2.0785421 | K68: =K67/J67-1 -> 0.14148741 | L68: =L67/K67-1 -> -0.12051713
A69: so it is near pre covid
A71: PARTICULARS | B71: 2021-22 | C71: 2022-23E | D71: 2023-24E | E71: 2024-25E | F71: 2025-26E | G71: 2026-27E
A72: SALES EXPECTED | B72: =E66 -> 748 | C72: 750 | D72: 750 | E72: 750 | F72: 750 | G72: 750
A73: GROWTH RATE | B73: =E67 -> -0.30547818 | C73: 0 | D73: 0 | E73: 0 | F73: 0 | G73: 0
H75: PARTICULARS | I75: 2021-22 | J75: 2022-23E | K75: 2023-24E | L75: 2024-25E | M75: 2025-26E | N75: 2026-27E
H76: SALES EXPECTED | I76: =L67 -> 12041 | J76: =I76*(1+J77) -> 13606.33 | K76: =J76*(1+K77) -> 15647.279 | L76: =K76*(1+L77) -> 17994.371 | M76: =L76*(1+M77) -> 20693.527 | N76: =Table141618[[#This Row],[2025-26E]]*(1+N77) -> 23797.556
H77: GROWTH RATE | I77: =L68 -> -0.12051713 | J77: 0.13 | K77: 0.15 | L77: 0.15 | M77: 0.15 | N77: 0.15
A79: Expected revenue | B79: Column1 | C79: 2022-23E | D79: 2023-24E | E79: 2024-25E | F79: 2025-26E | G79: 2026-27E
A80: =A27 -> OIL to Chemicals | C80: =C45 -> 536572.96 | D80: =D45 -> 590230.26 | E80: =E45 -> 649253.28 | F80: =F45 -> 714178.61 | G80: =G45 -> 785596.47
A81: =H27 -> OIL & gas | C81: =J38 -> 5323.4 | D81: =K38 -> 5722.655 | E81: =L38 -> 6151.8541 | F81: =M38 -> 6613.2432 | G81: =N38 -> 7109.2364
A82: =A48 -> ORGANISATION RETAIL | C82: =C61 -> 211968.08 | D82: =D61 -> 262840.42 | E82: =E61 -> 325922.12 | F82: =F61 -> 404143.43 | G82: =G61 -> 501137.85
A83: =H64 -> Digital Services | C83: =J76 -> 13606.33 | D83: =K76 -> 15647.279 | E83: =L76 -> 17994.371 | F83: =M76 -> 20693.527 | G83: =N76 -> 23797.556
A84: =A64 -> Financial services | C84: =C72 -> 750 | D84: =D72 -> 750 | E84: =E72 -> 750 | F84: =F72 -> 750 | G84: =G72 -> 750
A85: =H48 -> others | C85: =J55 -> 65718.96 | D85: =K55 -> 80177.131 | E85: =L55 -> 97816.1 | F85: =M55 -> 119335.64 | G85: =N55 -> 145589.48
A86: Total | C86: =SUBTOTAL(109,Table18[2022-23E]) -> 833939.73 | D86: =SUBTOTAL(109,Table18[2023-24E]) -> 955367.74 | E86: =SUBTOTAL(109,Table18[2024-25E]) -> 1097887.7 | F86: =SUBTOTAL(109,Table18[2025-26E]) -> 1265714.5 | G86: =SUBTOTAL(109,Table18[2026-27E]) -> 1463980.6
A90: other income | B90: =H7 -> 2018-19 | C90: =I7 -> 2019-20 | D90: =J7 -> 2020-21 | E90: =K7 -> 2021-22
B91: =H25 -> 8386 | C91: =I25 -> 13956 | D91: =J25 -> 16327 | E91: =K25 -> 14947
C92: =C91/B91-1 -> 0.66420224 | D92: =D91/C91-1 -> 0.16989109 | E92: =E91/D91-1 -> -0.08452257
A93: other income is based bon co plans on investment
A95: PARTICULARS | B95: 2021-22 | C95: 2022-23E | D95: 2023-24E | E95: 2024-25E | F95: 2025-26E | G95: 2026-27E
A96: SALES EXPECTED | B96: 12350 | C96: 12350 | D96: 12350 | E96: 12350 | F96: 12350 | G96: 12350
A97: GROWTH RATE | C97: 0 | D97: 0 | E97: 0 | F97: 0 | G97: 0

Sheet expenses
A1: PROFIT/LOSS | B1: Column1 | C1: 2018-19 | D1: 2019-20 | E1: 2020-21 | F1: 2021-22 | G1: Column2 | H1: 2022-23E | I1: 2023-24E | J1: 2024-25E | K1: 2025-26E | L1: 2026-27E
A2: =profitloss!A7 -> REVENUE FROM OPERATIONS | C2: =profitloss!C7 -> 583094 | D2: =profitloss!D7 -> 612437 | E2: =profitloss!E7 -> 486326 | F2: =profitloss!F7 -> 721634 | H2: =Table18[[#Totals],[2022-23E]] -> 833939.73 | I2: =Table18[[#Totals],[2023-24E]] -> 955367.74 | J2: =Table18[[#Totals],[2024-25E]] -> 1097887.7 | K2: =Table18[[#Totals],[2025-26E]] -> 1265714.5 | L2: =Table18[[#Totals],[2026-27E]] -> 1463980.6
A3: oyher income | E3: 6808 | F3: 4043 | H3: 5250 | I3: 5250 | J3: 5250 | K3: 5250 | L3: 5250
A4: expenses
A5: =profitloss!A11 -> Cost of Material Consumed | B5: =profitloss!B11 | C5: =profitloss!C11 -> 275237 | D5: =profitloss!D11 -> 260621 | E5: =profitloss!E11 -> 199915 | F5: =profitloss!F11 -> 360784 | H5: =H2*H6 -> 375272.88 | I5: =I2*I6 -> 429915.48 | J5: =J2*J6 -> 494049.48 | K5: =K2*K6 -> 569571.5 | L5: =L2*L6 -> 658791.27
A6: ="% of sales" & A5 -> % of salesCost of Material Consumed | C6: =C5/$C$2 -> 0.47202852 | D6: =D5/$D$2 -> 0.42554744 | E6: =E5/$E$2 -> 0.411072 | F6: =F5/$F$2 -> 0.49995427 | H6: 0.45 | I6: 0.45 | J6: 0.45 | K6: 0.45 | L6: 0.45
A7: =profitloss!A12 -> Purchase of Stock-in-Trade | B7: =profitloss!B12 | C7: =profitloss!C12 -> 123930 | D7: =profitloss!D12 -> 149667 | E7: =profitloss!E12 -> 101850 | F7: =profitloss!F12 -> 135585 | H7: =H2*H8 -> 183466.74 | I7: =I2*I8 -> 210180.9 | J7: =J2*J8 -> 241535.3 | K7: =K2*K8 -> 278457.18 | L7: =L2*L8 -> 322075.73
A8: ="% of sales" & A7 -> % of salesPurchase of Stock-in-Trade | C8: =C7/$C$2 -> 0.21253863 | D8: =D7/$D$2 -> 0.24437942 | E8: =E7/$E$2 -> 0.20942742 | F8: =F7/$F$2 -> 0.1878861 | H8: 0.22 | I8: 0.22 | J8: 0.22 | K8: 0.22 | L8: 0.22
A9: =profitloss!A13 -> Changes in Inventories of Finished Goods, Work-in-Progress and Stock-in-Trade | C9: =profitloss!C13 -> -4680 | D9: =profitloss!D13 -> -5048 | E9: =profitloss!E13 -> -9064 | F9: =profitloss!F13 -> -21457 | H9: -24540 | I9: -18570 | J9: -18540 | K9: -17450 | L9: -14850
A11: =profitloss!A14 -> Excise Duty | C11: =profitloss!C14 -> 13885 | D11: =profitloss!D14 -> 14902 | E11: =profitloss!E14 -> 19402 | F11: =profitloss!F14 -> 21672 | H11: =H2*H12 -> 20848.493 | I11: =I2*I12 -> 23884.194 | J11: =J2*J12 -> 27447.193 | K11: =K2*K12 -> 31642.861 | L11: =L2*L12 -> 36599.515
A12: ="% of sales" & A11 -> % of salesExcise Duty | C12: =C11/$C$2 -> 0.023812627 | D12: =D11/$D$2 -> 0.024332299 | E12: =E11/$E$2 -> 0.03989505 | F12: =F11/$F$2 -> 0.030031844 | H12: 0.025 | I12: 0.025 | J12: 0.025 | K12: 0.025 | L12: 0.025
A13: =profitloss!A15 -> Employee Benefits Expense | C13: =profitloss!C15 -> 12488 | D13: =profitloss!D15 -> 14075 | E13: =profitloss!E15 -> 14817 | F13: =profitloss!F15 -> 18775 | H13: =H14*H2 -> 25018.192 | I13: =I14*I2 -> 28661.032 | J13: =J14*J2 -> 32936.632 | K13: =K14*K2 -> 37971.434 | L13: =L14*L2 -> 43919.418
A14: ="% of sales" & A13 -> % of salesEmployee Benefits Expense | C14: =C13/$C$2 -> 0.021416787 | D14: =D13/$D$2 -> 0.022981956 | E14: =E13/$E$2 -> 0.030467217 | F14: =F13/$F$2 -> 0.026017344 | H14: 0.03 | I14: 0.03 | J14: 0.03 | K14: 0.03 | L14: 0.03
A15: =profitloss!A17 -> Depreciation/Amortisation and Depletion Expense | B15: =profitloss!B17 -> 1 | C15: =profitloss!C17 -> 20934 | D15: =profitloss!D17 -> 22203 | E15: =profitloss!E17 -> 26572 | F15: =profitloss!F17 -> 29797 | H15: =PPE!H85 -> 35113.252 | I15: =PPE!I85 -> 36394.962 | J15: =PPE!J85 -> 38187.399 | K15: =PPE!K85 -> 40502.862 | L15: =PPE!L85 -> 43377.203
A16: =profitloss!A18 -> Other Expenses | C16: =profitloss!C18 -> 78067 | D16: =profitloss!D18 -> 89211 | E16: =profitloss!E18 -> 78669 | F16: =profitloss!F18 -> 95815 | H16: =H21 -> 123307.41 | I16: =I21 -> 134877.04 | J16: =J21 -> 155145.2 | K16: =K21 -> 177752.88 | L16: =L21 -> 203009.79
A17: total exp without other | F17: =F5+F7+F11+F13+F15+F9+F16 -> 640971 | H17: =H5+H7+H9+H11+H13+H15 -> 615179.56 | I17: =I5+I7+I9+I11+I13+I15 -> 710466.57 | J17: =J5+J7+J9+J11+J13+J15 -> 815616 | K17: =K5+K7+K9+K11+K13+K15 -> 940695.84 | L17: =L5+L7+L9+L11+L13+L15 -> 1089913.1
A18: segment profit are before interest expenses and interest income | F18: =+F2+F3-F17 -> 84706 | G18: 0.12 | H18: =(H3+H2)*$G$18 -> 100702.77 | I18: =(I3+I2)*$G$18 -> 115274.13 | J18: =(J3+J2)*$G$18 -> 132376.53 | K18: =(K3+K2)*$G$18 -> 152515.73 | L18: =(L3+L2)*$G$18 -> 176307.67
A20: spendable part | H20: =H2+H3-H18 -> 738486.96 | I20: =I2+I3-I18 -> 845343.61 | J20: =J2+J3-J18 -> 970761.2 | K20: =K2+K3-K18 -> 1118448.7 | L20: =L2+L3-L18 -> 1292922.9
A21: other expenses | H21: =H20-H17 -> 123307.41 | I21: =I20-I17 -> 134877.04 | J21: =J20-J17 -> 155145.2 | K21: =K20-K17 -> 177752.88 | L21: =L20-L17 -> 203009.79
A23: Column1 | B23: Column2 | C23: Column3 | D23: Column4 | E23: Column5 | F23: Column6 | G23: Column7
A24: tax rate
A25: =+Table_0__2[[#This Row],[PROFIT/LOSS]] -> TAX EXPENSES | B25: =+Table_0__2[[#This Row],[Notes]] -> 0 | C25: =+Table_0__2[[#This Row],[2018-19]] -> 0 | D25: =profitloss!D24 -> 53606 | E25: =profitloss!E24 -> 55461 | F25: =profitloss!F24 -> 84142
A26: tax rate | C26: =SUM(profitloss!C26:C27) -> 15390 | D26: =SUM(profitloss!D26:D27) -> 13726 | E26: =SUM(profitloss!E26:E27) -> 1722 | F26: =SUM(profitloss!F26:F27) -> 16297 | G26: =SUM(profitloss!G26:G27) -> 18691.375
C28: =C26/C25 -> #DIV/0! | D28: =D26/D25 -> 0.25605343 | E28: =E26/E25 -> 0.031048845 | F28: =F26/F25 -> 0.19368449
A29: assumed tax rate | B29: 0.25

Sheet segmentrevenue
A1: 2020-21 | B1: Column1 | C1: O2C | D1: Gas | E1: Retail | F1: Services | G1: Services2 | H1: Others | I1: Unallocable | J1: Total | K1: Column2 | L1: O2C3 | M1: Gas4 | N1: Retail5 | O1: Services6 | P1: Services7 | Q1: Others8 | R1: Unallocable9 | S1: Total10
A3: Segment Revenue
A4: External Turnover | C4: 315105 | D4: 1608 | E4: 152501 | F4: 27336 | G4: 1114 | H4: 41574 | I4: - | J4: 539238 | L4: 499663 | M4: 4962 | N4: 195676 | O4: 27085 | P4: 761 | Q4: 64609 | R4: - | S4: 792756
A5: Inter Segment Turnover | C5: 4903 | D5: 532 | E5: 5201 | F5: 62951 | G5: 1324 | H5: 6646 | I5: - | L5: 1237 | M5: 2530 | N5: 4073 | O5: 73076 | P5: 1366 | Q5: 6751 | R5: - | S5: -
A7: Value of Sales and Services (Revenue) * | C7: 320008 | D7: 2140 | E7: 157702 | F7: 90287 | G7: 2438 | H7: 48220 | I7: - | J7: 539238 | L7: 500900 | M7: 7492 | N7: 199749 | O7: 100161 | P7: 2127 | Q7: 71360 | R7: - | S7: 792756
A9: Less: GST Recovered | C9: 13518 | D9: 12 | E9: 18566 | F9: 13645 | G9: 5 | H9: 7166 | J9: 52912 | L9: 20580 | M9: 10 | N9: 24734 | O9: 15044 | P9: 13 | Q9: 10741 | R9: - | S9: 71122
A10: Revenue from Operations (Net of GST) | C10: 306490 | D10: 2128 | E10: 139136 | F10: 76642 | G10: 2433 | H10: 41054 | I10: - | J10: 486326 | L10: 480320 | M10: 7482 | N10: 175015 | O10: 85117 | P10: 2114 | Q10: 60619 | R10: - | S10: 721634
A12: Segment Result before | C12: 29773 | D12: -1477 | E12: 7991 | F12: 21181 | G12: 1294 | H12: 3635 | I12: -1070 | J12: 61327 | L12: 45194 | M12: 2879 | N12: 10198 | O12: 25150 | P12: 708 | Q12: 5196 | R12: -4339 | S12: 84986
A13: Interest and Taxes **
A14: ^
A15: Finance Cost | J15: -21027 | S15: -14584
A17: Interest Income | J17: 9519 | S17: 10904
A19: Profit Before Tax and Exceptional Items | J19: 49819 | S19: 81306
A21: Exceptional Item (Net of Tax) | J21: 5642 | S21: 2836
A22: (Refer Note 31)
A23: Profit Before Tax | J23: 55461 | S23: 84142
S24: -3161
A25: Current Tax | J25: -2205
A26: Deferred Tax | J26: 483 | S26: -13136
A28: Non-Controlling | B28: Interest)
A29: Share of (Profit) | B29: / Loss transferred to | J29: -4611 | S29: 67845
A30: Non-Controlling | B30: Interest | S30: -7140
A31: Profit after Tax (after adjustment for | J31: 49128 | S31: 60705
A36: Other Information
A37: Segment Assets | B37: # | C37: 358964 | D37: 35163 | E37: 98361 | F37: 305965 | G37: 80765 | H37: 134717 | I37: 325455 | J37: 1339390 | L37: 379209 | M37: 34938 | N37: 124736 | O37: 371907 | P37: 108597 | Q37: 160961 | R37: 336206 | S37: 1516554
A39: Segment Liabilities | B39: # | C39: 44284 | D39: 14359 | E39: 20879 | F39: 68328 | G39: 93 | H39: 14272 | I39: 1177175 | J39: 1339390 | L39: 61336 | M39: 10899 | N39: 36031 | O39: 117938 | P39: 190 | Q39: 24371 | R39: 1265789 | S39: 1516554
A41: Capital Expenditure | C41: 7867 | D41: 3879 | E41: 10321 | F41: 35998 | G41: 18 | H41: 18289 | I41: 3295 | J41: 79667 | L41: 7913 | M41: 5520 | N41: 29873 | O41: 82744 | P41: 46 | Q41: 13606 | R41: 5650 | S41: 145352
A43: Depreciation / Amortisation and
C44: 8397 | D44: 1735 | E44: 1851 | F44: 12854 | G44: - | H44: 1376 | I44: 359 | J44: 26572 | L44: 7528 | M44: 2578 | N44: 2225 | O44: 15118 | P44: 15 | Q44: 1942 | R44: 391 | S44: 29797
A45: Depletion Expense
A48: Analysis | B48: Column1 | C48: O2C | D48: oil and gas | E48: retail | F48: digital | G48: financial | H48: other | I48: unallocated | J48: total | L48: Analysis | M48: Column1 | N48: O2C | O48: oil and gas | P48: retail | Q48: digital | R48: financial | S48: other | T48: unallocated | U48: total
A49: segment revenue | B49: =B10 -> 0 | C49: =C10 -> 306490 | D49: =D10 -> 2128 | E49: =E10 -> 139136 | F49: =F10 -> 76642 | G49: =G10 -> 2433 | H49: =H10 -> 41054 | I49: =I10 -> - | J49: =J10 -> 486326 | L49: segment revenue | N49: =L10 -> 480320 | O49: =M10 -> 7482 | P49: =N10 -> 175015 | Q49: =O10 -> 85117 | R49: =P7 -> 2127 | S49: =Q10 -> 60619 | T49: =T10 -> 0 | U49: =SUM(N49:T49) -> 810680
A50: segment profit are before interest expenses and interest income | L50: segment profit are before interest expenses and interest income
A51: segment profit | B51: =B12 -> 0 | C51: =C12 -> 29773 | D51: =D12 -> -1477 | E51: =E12 -> 7991 | F51: =F12 -> 21181 | G51: =G12 -> 1294 | H51: =H12 -> 3635 | I51: =I12 -> -1070 | J51: =J12 -> 61327 | L51: segment profit | N51: =L12 -> 45194 | O51: =M12 -> 2879 | P51: =N12 -> 10198 | Q51: =O12 -> 25150 | R51: =P12 -> 708 | S51: =Q12 -> 5196 | T51: =R12 -> -4339 | U51: =SUM(N51:T51) -> 84986
A53: profit % | C53: =C51/C49 -> 0.097141832 | D53: =D51/D49 -> -0.69407895 | E53: =E51/E49 -> 0.057433015 | F53: =F51/F49 -> 0.27636283 | G53: =G51/G49 -> 0.53185368 | H53: =H51/H49 -> 0.08854192 | J53: =J51/J49 -> 0.12610266 | L53: profit % | N53: =N51/N49 -> 0.094091439 | O53: =O51/O49 -> 0.38479016 | P53: =P51/P49 -> 0.058269291 | Q53: =Q51/Q49 -> 0.29547564 | R53: =R51/R49 -> 0.33286319 | S53: =S51/S49 -> 0.0857157 | U53: =U51/U49 -> 0.10483298
